Workbook

Sheet КАЛЬКУЛЯТОР
A1: КОД | B1: КОЛ-ВО | C1: СКИДКА | D1: НАИМЕНОВАНИЕ | E1: ББ | F1: ОП | G1: ПЦ
D2: С У М М А | E2: =SUM(E3:E900) -> 0 | F2: =SUM(F3:F900) -> 0 | G2: =SUM(G3:G900) -> 0
C3: =IF(A3=""," ",VLOOKUP(A3,'01.01.2026 - 24.01.2026'!A:H,2,FALSE)) | D3: =IF(A3=""," ",VLOOKUP(A3,'01.01.2026 - 24.01.2026'!A:H,5,FALSE)) | E3: =IF(A3=""," ",B3*VLOOKUP(A3,'01.01.2026 - 24.01.2026'!A:H,6,FALSE)) | F3: =IF(A3=""," ",B3*VLOOKUP(A3,'01.01.2026 - 24.01.2026'!A:H,7,FALSE)) | G3: =IF(A3=""," ",B3*VLOOKUP(A3,'01.01.2026 - 24.01.2026'!A:H,8,FALSE))
C4: =IF(A4=""," ",VLOOKUP(A4,'01.01.2026 - 24.01.2026'!A:H,2,FALSE)) | D4: =IF(A4=""," ",VLOOKUP(A4,'01.01.2026 - 24.01.2026'!A:H,5,FALSE)) | E4: =IF(A4=""," ",B4*VLOOKUP(A4,'01.01.2026 - 24.01.2026'!A:H,6,FALSE)) | F4: =IF(A4=""," ",B4*VLOOKUP(A4,'01.01.2026 - 24.01.2026'!A:H,7,FALSE)) | G4: =IF(A4=""," ",B4*VLOOKUP(A4,'01.01.2026 - 24.01.2026'!A:H,8,FALSE))
C5: =IF(A5=""," ",VLOOKUP(A5,'01.01.2026 - 24.01.2026'!A:H,2,FALSE)) | D5: =IF(A5=""," ",VLOOKUP(A5,'01.01.2026 - 24.01.2026'!A:H,5,FALSE)) | E5: =IF(A5=""," ",B5*VLOOKUP(A5,'01.01.2026 - 24.01.2026'!A:H,6,FALSE)) | F5: =IF(A5=""," ",B5*VLOOKUP(A5,'01.01.2026 - 24.01.2026'!A:H,7,FALSE)) | G5: =IF(A5=""," ",B5*VLOOKUP(A5,'01.01.2026 - 24.01.2026'!A:H,8,FALSE))
C6: =IF(A6=""," ",VLOOKUP(A6,'01.01.2026 - 24.01.2026'!A:H,2,FALSE)) | D6: =IF(A6=""," ",VLOOKUP(A6,'01.01.2026 - 24.01.2026'!A:H,5,FALSE)) | E6: =IF(A6=""," ",B6*VLOOKUP(A6,'01.01.2026 - 24.01.2026'!A:H,6,FALSE)) | F6: =IF(A6=""," ",B6*VLOOKUP(A6,'01.01.2026 - 24.01.2026'!A:H,7,FALSE)) | G6: =IF(A6=""," ",B6*VLOOKUP(A6,'01.01.2026 - 24.01.2026'!A:H,8,FALSE))
C7: =IF(A7=""," ",VLOOKUP(A7,'01.01.2026 - 24.01.2026'!A:H,2,FALSE)) | D7: =IF(A7=""," ",VLOOKUP(A7,'01.01.2026 - 24.01.2026'!A:H,5,FALSE)) | E7: =IF(A7=""," ",B7*VLOOKUP(A7,'01.01.2026 - 24.01.2026'!A:H,6,FALSE)) | F7: =IF(A7=""," ",B7*VLOOKUP(A7,'01.01.2026 - 24.01.2026'!A:H,7,FALSE)) | G7: =IF(A7=""," ",B7*VLOOKUP(A7,'01.01.2026 - 24.01.2026'!A:H,8,FALSE))
C8: =IF(A8=""," ",VLOOKUP(A8,'01.01.2026 - 24.01.2026'!A:H,2,FALSE)) | D8: =IF(A8=""," ",VLOOKUP(A8,'01.01.2026 - 24.01.2026'!A:H,5,FALSE)) | E8: =IF(A8=""," ",B8*VLOOKUP(A8,'01.01.2026 - 24.01.2026'!A:H,6,FALSE)) | F8: =IF(A8=""," ",B8*VLOOKUP(A8,'01.01.2026 - 24.01.2026'!A:H,7,FALSE)) | G8: =IF(A8=""," ",B8*VLOOKUP(A8,'01.01.2026 - 24.01.2026'!A:H,8,FALSE))
C9: =IF(A9=""," ",VLOOKUP(A9,'01.01.2026 - 24.01.2026'!A:H,2,FALSE)) | D9: =IF(A9=""," ",VLOOKUP(A9,'01.01.2026 - 24.01.2026'!A:H,5,FALSE)) | E9: =IF(A9=""," ",B9*VLOOKUP(A9,'01.01.2026 - 24.01.2026'!A:H,6,FALSE)) | F9: =IF(A9=""," ",B9*VLOOKUP(A9,'01.01.2026 - 24.01.2026'!A:H,7,FALSE)) | G9: =IF(A9=""," ",B9*VLOOKUP(A9,'01.01.2026 - 24.01.2026'!A:H,8,FALSE))
C10: =IF(A10=""," ",VLOOKUP(A10,'01.01.2026 - 24.01.2026'!A:H,2,FALSE)) | D10: =IF(A10=""," ",VLOOKUP(A10,'01.01.2026 - 24.01.2026'!A:H,5,FALSE)) | E10: =IF(A10=""," ",B10*VLOOKUP(A10,'01.01.2026 - 24.01.2026'!A:H,6,FALSE)) | F10: =IF(A10=""," ",B10*VLOOKUP(A10,'01.01.2026 - 24.01.2026'!A:H,7,FALSE)) | G10: =IF(A10=""," ",B10*VLOOKUP(A10,'01.01.2026 - 24.01.2026'!A:H,8,FALSE))
C11: =IF(A11=""," ",VLOOKUP(A11,'01.01.2026 - 24.01.2026'!A:H,2,FALSE)) | D11: =IF(A11=""," ",VLOOKUP(A11,'01.01.2026 - 24.01.2026'!A:H,5,FALSE)) | E11: =IF(A11=""," ",B11*VLOOKUP(A11,'01.01.2026 - 24.01.2026'!A:H,6,FALSE)) | F11: =IF(A11=""," ",B11*VLOOKUP(A11,'01.01.2026 - 24.01.2026'!A:H,7,FALSE)) | G11: =IF(A11=""," ",B11*VLOOKUP(A11,'01.01.2026 - 24.01.2026'!A:H,8,FALSE))
C12: =IF(A12=""," ",VLOOKUP(A12,'01.01.2026 - 24.01.2026'!A:H,2,FALSE)) | D12: =IF(A12=""," ",VLOOKUP(A12,'01.01.2026 - 24.01.2026'!A:H,5,FALSE)) | E12: =IF(A12=""," ",B12*VLOOKUP(A12,'01.01.2026 - 24.01.2026'!A:H,6,FALSE)) | F12: =IF(A12=""," ",B12*VLOOKUP(A12,'01.01.2026 - 24.01.2026'!A:H,7,FALSE)) | G12: =IF(A12=""," ",B12*VLOOKUP(A12,'01.01.2026 - 24.01.2026'!A:H,8,FALSE))
C13: =IF(A13=""," ",VLOOKUP(A13,'01.01.2026 - 24.01.2026'!A:H,2,FALSE)) | D13: =IF(A13=""," ",VLOOKUP(A13,'01.01.2026 - 24.01.2026'!A:H,5,FALSE)) | E13: =IF(A13=""," ",B13*VLOOKUP(A13,'01.01.2026 - 24.01.2026'!A:H,6,FALSE)) | F13: =IF(A13=""," ",B13*VLOOKUP(A13,'01.01.2026 - 24.01.2026'!A:H,7,FALSE)) | G13: =IF(A13=""," ",B13*VLOOKUP(A13,'01.01.2026 - 24.01.2026'!A:H,8,FALSE))
C14: =IF(A14=""," ",VLOOKUP(A14,'01.01.2026 - 24.01.2026'!A:H,2,FALSE)) | D14: =IF(A14=""," ",VLOOKUP(A14,'01.01.2026 - 24.01.2026'!A:H,5,FALSE)) | E14: =IF(A14=""," ",B14*VLOOKUP(A14,'01.01.2026 - 24.01.2026'!A:H,6,FALSE)) | F14: =IF(A14=""," ",B14*VLOOKUP(A14,'01.01.2026 - 24.01.2026'!A:H,7,FALSE)) | G14: =IF(A14=""," ",B14*VLOOKUP(A14,'01.01.2026 - 24.01.2026'!A:H,8,FALSE))
... C876: =IF(A876=""," ",VLOOKUP(A876,'01.01.2026 - 24.01.2026'!A:H,2,FALSE)) | D876: =IF(A876=""," ",VLOOKUP(A876,'01.01.2026 - 24.01.2026'!A:H,5,FALSE)) | E876: =IF(A876=""," ",B876*VLOOKUP(A876,'01.01.2026 - 24.01.2026'!A:H,6,FALSE)) | F876: =IF(A876=""," ",B876*VLOOKUP(A876,'01.01.2026 - 24.01.2026'!A:H,7,FALSE)) | G876: =IF(A876=""," ",B876*VLOOKUP(A876,'01.01.2026 - 24.01.2026'!A:H,8,FALSE))

Sheet 01.01.2026 - 24.01.2026
A1: КОД | B1: СКИДКА | C1: СТР. | D1: АКЦИЯ | E1: НАИМЕНОВАНИЕ | F1: ББ | G1: ОП | H1: ПЦ
A2: НОВИНКИ
A3: 46897 | B3: 0.57096774 | C3: 25 | E3: ВОДОСТОЙКАЯ ТУШЬ ДЛЯ РЕСНИЦ С ЭФФЕКТОМ ОШЕЛОМИТЕЛЬНОГО ОБЪЁМА THE ONE - ЧЁРНЫЙ | F3: 4 | G3: 249 | H3: 399
A4: 48552 | B4: 0.26755853 | C4: 132 | E4: ЧЕХОЛ ДЛЯ МЫЛА | F4: 2 | G4: 68 | H4: 219
A5: 48915 | C5: 120 | E5: ПОЛОТЕНЦЕ-ТЮРБАН ДЛЯ ВОЛОС | F5: 9 | G5: 281 | H5: 899
A6: 48918 | C6: 52 | E6: КРИОМАССАЖЁР ДЛЯ ЛИЦА | F6: 9 | G6: 281 | H6: 899
A7: КАТАЛОГ
E8: WELLOSOPHY
A9: 29699 | C9: 68 | E9: КОМПЛЕКС «МУЛЬТИВИТАМИНЫ И МИНЕРАЛЫ» ДЛЯ ДЕТЕЙ | F9: 23 | G9: 1531 | H9: 2450
A10: 37285 | C10: 65 | E10: СУХАЯ СМЕСЬ ДЛЯ КОКТЕЙЛЯ NATURAL BALANCE - КЛУБНИЧНЫЙ ВКУС | F10: 52 | G10: 3406 | H10: 5450
A11: 37289 | C11: 65 | E11: СУХАЯ СМЕСЬ ДЛЯ КОКТЕЙЛЯ NATURAL BALANCE - ШОКОЛАДНЫЙ ВКУС | F11: 52 | G11: 3406 | H11: 5450
A12: 37290 | C12: 65 | E12: СУХАЯ СМЕСЬ ДЛЯ КОКТЕЙЛЯ NATURAL BALANCE - ВАНИЛЬНЫЙ ВКУС | F12: 52 | G12: 3406 | H12: 5450
A13: 38556 | C13: 161 | E13: КОМПЛЕКС «ОМЕГА-3» | F13: 26 | G13: 1687 | H13: 2700
A14: 38557 | C14: 70 | E14: КОМПЛЕКС «АСТАКСАНТИН И ЭКСТРАКТ ЧЕРНИКИ» | F14: 32 | G14: 2062 | H14: 3300
A15: 38558 | C15: 70 | E15: КОМПЛЕКС «МУЛЬТИВИТАМИНЫ И МИНЕРАЛЫ» ДЛЯ МУЖЧИН | F15: 32 | G15: 2062 | H15: 3300
A16: 38559 | C16: 70 | E16: КОМПЛЕКС «МУЛЬТИВИТАМИНЫ И МИНЕРАЛЫ» ДЛЯ ЖЕНЩИН | F16: 32 | G16: 2062 | H16: 3300
A17: 38836 | C17: 69 | E17: WELLOSOPHY WELLNESS PACK ДЛЯ МУЖЧИН | F17: 50 | G17: 3218 | H17: 5150
A18: 38838 | C18: 69 | E18: WELLOSOPHY WELLNESS PACK ДЛЯ ЖЕНЩИН | F18: 50 | G18: 3218 | H18: 5150
A19: 40745 | C19: 66 | E19: ПИТАТЕЛЬНЫЙ СУП ДЛЯ КОНТРОЛЯ ВЕСА - ГРИБНОЙ ВКУС | F19: 70 | G19: 4156 | H19: 6650
A20: 44220 | C20: 70 | E20: ВИТАМИН D3 | F20: 19 | G20: 1219 | H20: 1950
A21: 44221 | C21: 70 | E21: КОМПЛЕКС «МОРСКОЙ МАГНИЙ И ВИТАМИН B6» | F21: 22 | G21: 1437 | H21: 2300
A22: 45138 | B22: 0.23857143 | C22: 61 | E22: КРЕМ ДЛЯ ЛИЦА WELLOSOPHY-РАЗГЛАЖИВАНИЕ И ОБНОВЛЕНИЕ | F22: 15 | G22: 999 | H22: 1599
A23: 45139 | B23: 0.24566038 | C23: 61 | E23: ГЕЛЬ-СЫВОРОТКА ДЛЯ ЛИЦА WELLOSOPHY-ОМОЛОЖЕНИЕ И ВОССТАНОВЛЕНИЕ | F23: 19 | G23: 1250 | H23: 1999
A24: 45147 | E24: МАСЛО-СЫВОРОТКА WELLOSOPHY - УПРУГОСТЬ И СИЯНИЕ | F24: 20 | G24: 1312 | H24: 2100
A25: 45148 | B25: 0.29 | C25: 61 | E25: БАЛЬЗАМ ДЛЯ КОЖИ ВОКРУГ ГЛАЗ WELLOSOPHY-УВЛАЖНЕНИЕ И ВОССТАНОВЛЕНИЕ | F25: 13 | G25: 843 | H25: 1349
A26: 45149 | B26: 0.24206897 | C26: 61 | E26: ОЧИЩАЮЩЕЕ СРЕДСТВО ДЛЯ ЛИЦА WELLOSOPHY-СИЯНИЕ И БАЛАНС | F26: 11 | G26: 687 | H26: 1099
A27: 45152 | B27: 0.34636364 | C27: 59 | E27: МАСКА ДЛЯ ЛИЦА WELLOSOPHY - ОТШЕЛУШИВАНИЕ И ТОНИЗИРОВАНИЕ | F27: 7 | G27: 449 | H27: 719
A28: 45273 | C28: 70 | E28: НУТРИКОМПЛЕКС ДЛЯ КОЖИ, ВОЛОС И НОГТЕЙ | F28: 39 | G28: 2562 | H28: 4100
A29: 45290 | B29: 0.35241379 | C29: 58 | E29: МИСТ ДЛЯ ЛИЦА WELLOSOPHY - ВОССТАНОВЛЕНИЕ И УВЛАЖНЕНИЕ | F29: 9 | G29: 587 | H29: 939
A30: 45306 | C30: 67 | E30: ПИТАТЕЛЬНЫЙ КОКТЕЙЛЬ ДЛЯ КОНТРОЛЯ ВЕСА - ВАНИЛЬНЫЙ ВКУС | F30: 70 | G30: 4156 | H30: 6650
A31: 45307 | C31: 67 | E31: ПИТАТЕЛЬНЫЙ КОКТЕЙЛЬ ДЛЯ КОНТРОЛЯ ВЕСА - ШОКОЛАДНЫЙ ВКУС | F31: 70 | G31: 4156 | H31: 6650
A32: 45309 | C32: 70 | E32: КОМПЛЕКС "МОРСКОЙ КАЛЬЦИЙ И ВИТАМИН D" | F32: 26 | G32: 1687 | H32: 2700
A33: 45312 | B33: 0.40777778 | C33: 71 | E33: ПРЕБИОТИЧЕСКИЙ НАПИТОК С ПИЩЕВЫМИ ВОЛОКНАМИ | F33: 15 | G33: 999 | H33: 1599
A34: 46068 | C34: 71 | E34: МЕРНАЯ ЛОЖКА | F34: 1 | G34: 46 | H34: 149
A35: 46664 | C35: 66 | E35: ШЕЙКЕР | F35: 15 | G35: 500 | H35: 1599
A36: 47784 | B36: 0.39815534 | C36: 63 | E36: НАБОР ДЛЯ УХОДА ЗА КОЖЕЙ WELLOSOPHY+НУТРИКОМПЛЕКС | F36: 59 | G36: 3875 | H36: 6199
A37: 47785 | B37: 0.40010526 | C37: 62 | E37: БАЗОВЫЙ НАБОР ДЛЯ УХОДА ЗА КОЖЕЙ+КОМПЛЕКС "АСТАКСАНТИН И ЭКСТРАКТ ЧЕРНИКИ" | F37: 65 | G37: 3562 | H37: 5699
A38: 47788 | B38: 0.40108911 | C38: 63 | E38: НАБОР WELLOSOPHY+КОМПЛЕКС"МОРСКОЙ МАГНИЙ И ВИТАМИН B6" | F38: 58 | G38: 3781 | H38: 6049
A39: 47847 | B39: 0.4033871 | C39: 60 | E39: БАЗОВЫЙ НАБОР ДЛЯ УХОДА ЗА КОЖЕЙ WELLOSOPHY | F39: 42 | G39: 2312 | H39: 3699
E40: ДЕКОРАТИВНАЯ КОСМЕТИКА
E41: ПОМАДЫ, БЛЕСКИ И КАРАНДАШИ ДЛЯ ГУБ
A42: 37728 | B42: 0.53888889 | C42: 87 | E42: КАРАНДАШ ДЛЯ ГУБ THE ONE - НЮД | F42: 2 | G42: 156 | H42: 249
A43: 37729 | B43: 0.53888889 | C43: 87 | E43: - КАРАМЕЛЬ | F43: 2 | G43: 156 | H43: 249
A44: 37730 | B44: 0.53888889 | C44: 87 | E44: - ПЫЛЬНАЯ РОЗА | F44: 2 | G44: 156 | H44: 249
A45: 37734 | B45: 0.53888889 | C45: 87 | E45: - КРАСНЫЙ | F45: 2 | G45: 156 | H45: 249
A46: 37735 | B46: 0.53888889 | C46: 87 | E46: - ВИННЫЙ | F46: 2 | G46: 156 | H46: 249
A47: 37736 | B47: 0.53888889 | C47: 87 | E47: - СЛИВОВЫЙ | F47: 2 | G47: 156 | H47: 249
A48: 37737 | B48: 0.53888889 | C48: 87 | E48: - ШОКОЛАДНЫЙ | F48: 2 | G48: 156 | H48: 249
A49: 38863 | B49: 0.45221239 | C49: 88 | E49: ГЛЯНЦЕВАЯ ГУБНАЯ ПОМАДА-КУШОН THE ONE IRRESISTIBLE TOUCH - ЧАРУЮЩАЯ РОЗА | F49: 6 | G49: 387 | H49: 619
A50: 38864 | B50: 0.45221239 | C50: 88 | E50: - СОБЛАЗНИТЕЛЬНЫЙ ТАУП | F50: 6 | G50: 387 | H50: 619
A51: 38865 | B51: 0.45221239 | C51: 88 | E51: - ОБВОРОЖИТЕЛЬНЫЙ НЮД | F51: 6 | G51: 387 | H51: 619
A52: 38866 | B52: 0.45221239 | C52: 88 | E52: - СЛАДКАЯ КАРАМЕЛЬ | F52: 6 | G52: 387 | H52: 619
A53: 38867 | B53: 0.45221239 | C53: 88 | E53: - ГОРЯЧИЙ ШОКОЛАД | F53: 6 | G53: 387 | H53: 619
... A138: 47182 | B138: 0.64357143 | C138: 93 | E138: - НЕЖНЫЙ ПЕРСИКОВЫЙ | F138: 5 | G138: 312 | H138: 499
E139: ТУШЬ ДЛЯ РЕСНИЦ
A140: 38929 | B140: 0.5328125 | C140: 21 | E140: ОБЪЕМНАЯ ТУШЬ ДЛЯ РЕСНИЦ ONCOLOUR - ЧЕРНЫЙ | F140: 3 | G140: 187 | H140: 299
A141: 42120 | B141: 0.56071429 | C141: 23 | E141: ВОДОСТОЙКАЯ ТУШЬ ДЛЯ РЕСНИЦ 5 В 1 THE ONE WONDERLASH - ЧЁРНЫЙ | F141: 4 | G141: 231 | H141: 369
A142: 42273 | B142: 0.5328125 | C142: 21 | E142: ОБЪЕМНАЯ ВОДОСТОЙКАЯ ТУШЬ ДЛЯ РЕСНИЦ ONCOLOUR - ЧЕРНЫЙ | F142: 3 | G142: 187 | H142: 299
A143: 42780 | B143: 0.56972477 | C143: 85 | E143: ТУШЬ ДЛЯ РЕСНИЦ THE ONE DOUBLE EFFECT - ЧЁРНЫЙ | F143: 4 | G143: 293 | H143: 469
A144: 43123 | B144: 0.56071429 | C144: 22 | E144: ТУШЬ ДЛЯ РЕСНИЦ 5 В 1 THE ONE C ЭФФЕКТОМ HD - ЧЁРНЫЙ | F144: 4 | G144: 231 | H144: 369
A145: 46896 | B145: 0.57096774 | C145: 24 | E145: ТУШЬ ДЛЯ РЕСНИЦ С ЭФФЕКТОМ ОБЪЁМА THE ONE ЧЁРНЫЙ | F145: 4 | G145: 249 | H145: 399
A146: 48650 | B146: 0.56071429 | C146: 23 | E146: МНОГОФУНКЦИОНАЛЬНАЯ ВОДОСТОЙКАЯ ТУШЬ ДЛЯ РЕСНИЦ 5 В 1 THE ONE WONDER LASH. ЛИМИТИРОВАННЫЙ ВЫПУСК - ЧЁРНЫЙ | F146: 4 | G146: 231 | H146: 369
A147: 46969 | B147: 0.40125 | C147: 118 | E147: ТУШЬ ДЛЯ РЕСНИЦ С ЭФФЕКТОМ ОБЪЁМА THE ONE ЧЁРНЫЙ | F147: 5 | G147: 299 | H147: 479
A148: 44655 | B148: 0.44529915 | C148: 27 | E148: ВОДОСТОЙКАЯ СУПЕРТУШЬ ДЛЯ РЕСНИЦ GIORDANI GOLD | F148: 6 | G148: 406 | H148: 649
A149: 47835 | B149: 0.48125 | C149: 85 | E149: ЩИПЧИКИ ДЛЯ ЗАВИВКИ РЕСНИЦ | F149: 2 | G149: 78 | H149: 249
E150: КАРАНДАШИ ДЛЯ ГЛАЗ И БРОВЕЙ, ПОДВОДКА ДЛЯ ГЛАЗ, ПОМАДА И ТЕНИ ДЛЯ БРОВЕЙ
A151: 41367 | B151: 0.54561404 | C151: 101 | E151: ДВУСТОРОННИЙ КАРАНДАШ ДЛЯ ГЛАЗ ONCOLOUR - СНЕГ И ГРАФИТ | F151: 2 | G151: 162 | H151: 259
A152: 41368 | B152: 0.54561404 | C152: 101 | E152: - МОККО И РОЗОВОЕ ЗОЛОТО | F152: 2 | G152: 162 | H152: 259
A153: 41369 | B153: 0.54561404 | C153: 101 | E153: - САПФИР И ОКЕАН | F153: 2 | G153: 162 | H153: 259
A154: 41370 | B154: 0.54561404 | C154: 101 | E154: - ПАЛЬМА И ОЛИВКА | F154: 2 | G154: 162 | H154: 259
A155: 43206 | B155: 0.3967033 | C155: 80 | E155: ТУШЬ ДЛЯ БРОВЕЙ THE ONE - КОРИЧНЕВЫЙ | F155: 5 | G155: 343 | H155: 549
A156: 43207 | B156: 0.3967033 | C156: 80 | E156: - ТЁМНО-КОРИЧНЕВЫЙ | F156: 5 | G156: 343 | H156: 549
A157: 43347 | B157: 0.46733333 | C157: 83 | E157: ТЕНИ-ПОДВОДКА ДЛЯ ВЕК THE ONE COLOUR UNLIMITED - ЗЕЛЁНЫЙ ИЗУМРУД | F157: 8 | G157: 500 | H157: 799
A158: 43348 | B158: 0.46733333 | C158: 83 | E158: - ИГРИСТЫЙ НЮД | F158: 8 | G158: 500 | H158: 799
A159: 43350 | B159: 0.46733333 | C159: 83 | E159: - РОЗОВЫЙ ЗАКАТ | F159: 8 | G159: 500 | H159: 799
A160: 43985 | B160: 0.39596774 | C160: 80 | E160: МАРКЕР ДЛЯ БРОВЕЙ THE ONE - СВЕТЛО-КОРИЧНЕВЫЙ | F160: 7 | G160: 468 | H160: 749
A161: 43986 | B161: 0.39596774 | C161: 80 | E161: - КОРИЧНЕВЫЙ | F161: 7 | G161: 468 | H161: 749
A162: 43987 | B162: 0.39596774 | C162: 80 | E162: - ТЁМНО-КОРИЧНЕВЫЙ | F162: 7 | G162: 468 | H162: 749
... A168: 47708 | B168: 0.48333333 | C168: 84 | E168: - ИЗУМРУДНЫЙ | F168: 3 | G168: 174 | H168: 279
E169: ТЕНИ ДЛЯ ВЕК
A170: 45361 | B170: 0.46176471 | C170: 82 | E170: ЖИДКИЕ ТЕНИ С ЭФФЕКТОМ "МЕТАЛЛИК" THE ONE - РОЗОВЫЙ | F170: 5 | G170: 343 | H170: 549
A171: 45362 | B171: 0.46176471 | C171: 82 | E171: - ПЕРСИКОВЫЙ | F171: 5 | G171: 343 | H171: 549
A172: 45364 | B172: 0.46176471 | C172: 82 | E172: - БЕЖЕВЫЙ | F172: 5 | G172: 343 | H172: 549
A173: 46351 | B173: 0.46733333 | C173: 83 | E173: СТОЙКИЕ ТЕНИ-ПОДВОДКА ДЛЯ ВЕК THE ONE COLOUR UNLIMITED - БЕЗУПРЕЧНЫЙ ПЕРСИК | F173: 8 | G173: 500 | H173: 799
A174: 46352 | B174: 0.46733333 | C174: 83 | E174: - БРОНЗОВЫЙ ПЕСОК | F174: 8 | G174: 500 | H174: 799
A175: 46353 | B175: 0.46733333 | C175: 83 | E175: - СЕРЫЙ ГРАНИТ | F175: 8 | G175: 500 | H175: 799
A176: 47189 | B176: 0.334 | C176: 82 | E176: ЖИДКИЕ ТЕНИ ДЛЯ ВЕК THE ONE - МЕРЦАНИЕ ЗВЁЗД | F176: 10 | G176: 624 | H176: 999
A177: 47190 | B177: 0.334 | C177: 82 | E177: - МАГИЯ ЗОЛОТА | F177: 10 | G177: 624 | H177: 999
A178: 47191 | B178: 0.334 | C178: 82 | E178: - ВОЛШЕБНАЯ НОЧЬ | F178: 10 | G178: 624 | H178: 999
A179: 47192 | B179: 0.334 | C179: 82 | E179: - СНЕЖНОЕ СИЯНИЕ | F179: 10 | G179: 624 | H179: 999
E180: ТОНАЛЬНЫЕ ОСНОВЫ, РУМЯНА, ПУДРЫ, КОНСИЛЛЕРЫ
A181: 41107 | B181: 0.44176471 | C181: 74 | E181: КОНСИЛЕР С ПРЕБИОТИЧЕСКОЙ СЫВОРОТКОЙ GIORDANI GOLD - СВЕТЛЫЙ | F181: 9 | G181: 593 | H181: 949
A182: 41108 | B182: 0.44176471 | C182: 74 | E182: - СРЕДНИЙ | F182: 9 | G182: 593 | H182: 949
A183: 41989 | B183: 0.475 | C183: 79 | E183: АДАПТИВНЫЙ КОНСИЛЕР THE ONE EVERLASTING SYNC - ХОЛОДНЫЙ ФАРФОРОВЫЙ | F183: 4 | G183: 249 | H183: 399
A184: 41990 | B184: 0.475 | C184: 79 | E184: - ЕСТЕСТВЕННЫЙ БЕЖ | F184: 4 | G184: 249 | H184: 399
A185: 41991 | B185: 0.475 | C185: 79 | E185: - ТЁПЛЫЙ БЕЖ | F185: 4 | G185: 249 | H185: 399
A186: 42118 | B186: 0.43928571 | C186: 74 | E186: АНТИВОЗРАСТНАЯ ОСНОВА ПОД МАКИЯЖ С ПРЕБИОТИЧЕСКОЙ СЫВОРОТКОЙ GIORDANI GOLD | F186: 11 | G186: 687 | H186: 1099
A187: 42121 | B187: 0.40567568 | C187: 76 | E187: ПАЛЕТКА ДЛЯ МАКИЯЖА GIORDANI GOLD | F187: 21 | G187: 1374 | H187: 2199
A188: 42236 | B188: 0.42904762 | C188: 75 | E188: АНТИВОЗРАСТНАЯ ТОН. ОСНОВА С ПРЕБИОТИЧЕСКОЙ СЫВОРОТКОЙ GIORDANI GOLD SPF 12 - ВАНИЛЬНЫЙ (НЕЙТРАЛЬНЫЙ) | F188: 11 | G188: 749 | H188: 1199
A189: 42237 | B189: 0.42904762 | C189: 75 | E189: - ВАНИЛЬНЫЙ (ХОЛОДНЫЙ) | F189: 11 | G189: 749 | H189: 1199
...
