Workbook
Name Color_GM: #REF!
Name Target_GM: #REF!
Name МЯГКИЙ_ДВУХСТОРОННИЙ_КАРАНДАШ_ДЛЯ_ГЛАЗ___СЛИВОЧНАЯ_КАРАМЕЛЬ__СТР._83_КАТАЛОГА: '[1]10 КАТАЛОГ`08 (1)'!#REF!
Name МЯГКИЙ_ДВУХСТОРОННИЙ_КАРАНДАШ_ДЛЯ_ГЛАЗ___СЛИВОЧНАЯ_КАРАМЕЛЬ__СТР._83_КАТАЛОГА: '[1]10 КАТАЛОГ`08 (1)'!#REF!
Name МЯГКИЙ_ДВУХСТОРОННИЙ_КАРАНДАШ_ДЛЯ_ГЛАЗ___СЛИВОЧНАЯ_КАРАМЕЛЬ__СТР._83_КАТАЛОГА: '05 КАТАЛОГ`26 (1)'!#REF!

Sheet 05 КАТАЛОГ`26 (1)
E1: НОВИНКИ КАТАЛОГА
A2: КОД | B2: СКИДКА | C2: СТР. | D2: АКЦИЯ | E2: НАИМЕНОВАНИЕ | F2: ББ | G2: ОП | H2: ПЦ
A3: 45286 | B3: 0.39052632 | C3: 17 | E3: ОТШЕЛУШИВАЮЩИЙ СКРАБ ДЛЯ ЛИЦА OPTIMALS | F3: 5 | G3: 356 | H3: 579
A4: 45287 | B4: 0.39052632 | C4: 10 | E4: МИЦЕЛЛЯРНАЯ ВОДА OPTIMALS | F4: 5 | G4: 356 | H4: 579
A5: 47278 | B5: 0.39052632 | C5: 11 | E5: УВЛАЖНЯЮЩИЙ ТОНИК OPTIMALS | F5: 5 | G5: 356 | H5: 579
A6: 47682 | B6: 0.400625 | C6: 15 | E6: ЛЁГКИЙ АНТИВОЗРАСТНОЙ КРЕМ ДЛЯ ЛИЦА OPTIMALS | F6: 9 | G6: 590 | H6: 959
A7: 47683 | B7: 0.400625 | C7: 15 | E7: НАСЫЩЕННЫЙ АНТИВОЗРАСТНОЙ КРЕМ ДЛЯ ЛИЦА OPTIMALS | F7: 9 | G7: 590 | H7: 959
A8: 47684 | B8: 0.3937931 | C8: 13 | E8: РАЗГЛАЖИВАЮЩИЙ КРЕМ-ФИЛЛЕР ДЛЯ ЛИЦА OPTIMALS | F8: 8 | G8: 540 | H8: 879
A9: 47685 | B9: 0.400625 | C9: 14 | E9: АНТИВОЗРАСТНАЯ СЫВОРОТКА OPTIMALS | F9: 9 | G9: 590 | H9: 959
A10: 48656 | B10: 0.562 | C10: 47 | E10: ОТТЕНОЧНЫЙ БАЛЬЗАМ ДЛЯ ГУБ ONCOLOUR - ВАНИЛЬНЫЙ КРУАССАН | F10: 2 | G10: 134 | H10: 219
A11: 48657 | B11: 0.562 | C11: 47 | E11: - ТЁПЛЫЙ ГЛИНТВЕЙН | F11: 2 | G11: 134 | H11: 219
A12: 48658 | B12: 0.562 | C12: 47 | E12: - РОЗОВЫЙ МАРМЕЛАД | F12: 2 | G12: 134 | H12: 219
A13: 48659 | B13: 0.562 | C13: 47 | E13: - ВИШНЁВОЕ ЖЕЛЕ | F13: 2 | G13: 134 | H13: 219
A14: 48938 | C14: 14 | E14: АНТИВОЗРАСТНАЯ СЫВОРОТКА OPTIMALS (ПРОБНИК) | F14: - | G14: - | H14: 40
A15: 48939 | C15: 15 | E15: НАСЫЩЕННЫЙ АНТИВОЗРАСТНОЙ КРЕМ ДЛЯ ЛИЦА OPTIMALS (ПРОБНИК) | F15: - | G15: - | H15: 40
A16: 48940 | C16: 15 | E16: ЛЁГКИЙ АНТИВОЗРАСТНОЙ КРЕМ ДЛЯ ЛИЦА OPTIMALS (ПРОБНИК) | F16: - | G16: - | H16: 40
E18: НОВИНКИ WELLOSOPHY
A19: КОД | B19: СКИДКА | C19: СТР. | D19: АКЦИЯ | E19: НАИМЕНОВАНИЕ | F19: ББ | G19: ОП | H19: ПЦ
A20: 48896 | B20: 0.2538806 | C20: 7 | E20: КОМПЛЕКС ORIMETABO RE-BALANCE | F20: 47 | G20: 3073 | H20: 4999
E22: WELLOSOPHY
A23: КОД | B23: СКИДКА | C23: СТР. | D23: АКЦИЯ | E23: НАИМЕНОВАНИЕ | F23: ББ | G23: ОП | H23: ПЦ
A24: 29699 | C24: 113 | E24: КОМПЛЕКС «МУЛЬТИВИТАМИНЫ И МИНЕРАЛЫ» ДЛЯ ДЕТЕЙ | F24: 24 | G24: 1537 | H24: 2500
A25: 37285 | C25: 115 | E25: СУХАЯ СМЕСЬ ДЛЯ КОКТЕЙЛЯ NATURAL BALANCE - КЛУБНИЧНЫЙ ВКУС | F25: 54 | G25: 3442 | H25: 5600
A26: 37289 | C26: 115 | E26: СУХАЯ СМЕСЬ ДЛЯ КОКТЕЙЛЯ NATURAL BALANCE - ШОКОЛАДНЫЙ ВКУС | F26: 54 | G26: 3442 | H26: 5600
A27: 37290 | C27: 115 | E27: СУХАЯ СМЕСЬ ДЛЯ КОКТЕЙЛЯ NATURAL BALANCE - ВАНИЛЬНЫЙ ВКУС | F27: 54 | G27: 3442 | H27: 5600
A28: 38556 | B28: 0.25035714 | C28: 119 | E28: КОМПЛЕКС «ОМЕГА-3» | F28: 20 | G28: 1290 | H28: 2099
A29: 38557 | C29: 117 | E29: КОМПЛЕКС «АСТАКСАНТИН И ЭКСТРАКТ ЧЕРНИКИ» | F29: 33 | G29: 2121 | H29: 3450
A30: 38558 | C30: 118 | E30: КОМПЛЕКС «МУЛЬТИВИТАМИНЫ И МИНЕРАЛЫ» ДЛЯ МУЖЧИН | F30: 33 | G30: 2121 | H30: 3450
A31: 38559 | C31: 118 | E31: КОМПЛЕКС «МУЛЬТИВИТАМИНЫ И МИНЕРАЛЫ» ДЛЯ ЖЕНЩИН | F31: 33 | G31: 2121 | H31: 3450
A32: 38836 | C32: 113 | E32: WELLOSOPHY WELLNESS PACK ДЛЯ МУЖЧИН | F32: 51 | G32: 3258 | H32: 5300
A33: 38838 | C33: 113 | E33: WELLOSOPHY WELLNESS PACK ДЛЯ ЖЕНЩИН | F33: 51 | G33: 3258 | H33: 5300
A34: 40745 | C34: 114 | E34: ПИТАТЕЛЬНЫЙ СУП ДЛЯ КОНТРОЛЯ ВЕСА - ГРИБНОЙ ВКУС | F34: 70 | G34: 4242 | H34: 6900
A35: 44220 | B35: 0.4005 | C35: 121 | E35: ВИТАМИН D3 | F35: 11 | G35: 737 | H35: 1199
A36: 44221 | C36: 120 | E36: КОМПЛЕКС «МОРСКОЙ МАГНИЙ И ВИТАМИН B6» | F36: 23 | G36: 1476 | H36: 2400
A37: 45138 | B37: 0.25045455 | C37: 110 | E37: КРЕМ ДЛЯ ЛИЦА WELLOSOPHY-РАЗГЛАЖИВАНИЕ И ОБНОВЛЕНИЕ | F37: 16 | G37: 1013 | H37: 1649
A38: 45147 | B38: 0.50045455 | C38: 25 | E38: МАСЛО-СЫВОРОТКА WELLOSOPHY - УПРУГОСТЬ И СИЯНИЕ | F38: 10 | G38: 675 | H38: 1099
A39: 45148 | B39: 0.3005 | C39: 110 | E39: БАЛЬЗАМ ДЛЯ КОЖИ ВОКРУГ ГЛАЗ WELLOSOPHY-УВЛАЖНЕНИЕ И ВОССТАНОВЛЕНИЕ | F39: 13 | G39: 860 | H39: 1399
A40: 45149 | B40: 0.40066667 | C40: 110 | E40: ОЧИЩАЮЩЕЕ СРЕДСТВО ДЛЯ ЛИЦА WELLOSOPHY-СИЯНИЕ И БАЛАНС | F40: 8 | G40: 552 | H40: 899
A41: 45273 | C41: 120 | E41: НУТРИКОМПЛЕКС ДЛЯ КОЖИ, ВОЛОС И НОГТЕЙ | F41: 41 | G41: 2613 | H41: 4250
A42: 45289 | B42: 0.49757576 | C42: 24 | E42: НОЧНОЙ ЭЛИКСИР WELLOSOPHY-ВОССТАНОВЛЕНИЕ И РАЗГЛАЖИВАНИЕ | F42: 8 | G42: 509 | H42: 829
A43: 45290 | B43: 0.50066667 | C43: 24 | E43: МИСТ ДЛЯ ЛИЦА WELLOSOPHY-ВОССТАНОВЛЕНИЕ И УВЛАЖНЕНИЕ | F43: 7 | G43: 460 | H43: 749
A44: 45306 | C44: 114 | E44: ПИТАТЕЛЬНЫЙ КОКТЕЙЛЬ ДЛЯ КОНТРОЛЯ ВЕСА - ВАНИЛЬНЫЙ ВКУС | F44: 70 | G44: 4242 | H44: 6900
A45: 45307 | C45: 114 | E45: ПИТАТЕЛЬНЫЙ КОКТЕЙЛЬ ДЛЯ КОНТРОЛЯ ВЕСА - ШОКОЛАДНЫЙ ВКУС | F45: 70 | G45: 4242 | H45: 6900
A46: 45309 | C46: 120 | E46: КОМПЛЕКС "МОРСКОЙ КАЛЬЦИЙ И ВИТАМИН D" | F46: 27 | G46: 1721 | H46: 2800
A47: 45312 | C47: 116 | E47: ПРЕБИОТИЧЕСКИЙ НАПИТОК С ПИЩЕВЫМИ ВОЛОКНАМИ | F47: 27 | G47: 1721 | H47: 2800
A48: 46068 | C48: 114 | E48: МЕРНАЯ ЛОЖКА | F48: 1 | G48: 46 | H48: 149
A49: 46664 | C49: 115 | E49: ШЕЙКЕР | F49: 15 | G49: 491 | H49: 1599
A50: 47784 | B50: 0.40103774 | C50: 111 | E50: НАБОР ДЛЯ УХОДА ЗА КОЖЕЙ WELLOSOPHY+НУТРИКОМПЛЕКС | F50: 60 | G50: 3903 | H50: 6349
A51: 47847 | B51: 0.40173228 | C51: 111 | E51: БАЗОВЫЙ НАБОР ДЛЯ УХОДА ЗА КОЖЕЙ WELLOSOPHY | F51: 43 | G51: 2335 | H51: 3799
E53: КАТАЛОГ
A54: КОД | B54: СКИДКА | C54: СТР. | D54: АКЦИЯ | E54: НАИМЕНОВАНИЕ | F54: ББ | G54: ОП | H54: ПЦ
E55: ДЕКОРАТИВНАЯ КОСМЕТИКА
E56: ПОМАДЫ, БЛЕСКИ И КАРАНДАШИ ДЛЯ ГУБ
A57: 37728 | B57: 0.64464286 | C57: 26 | E57: КАРАНДАШ ДЛЯ ГУБ THE ONE - НЮД | F57: 2 | G57: 122 | H57: 199
A58: 37729 | B58: 0.64464286 | C58: 26 | E58: - КАРАМЕЛЬ | F58: 2 | G58: 122 | H58: 199
A59: 37730 | B59: 0.64464286 | C59: 26 | E59: - ПЫЛЬНАЯ РОЗА | F59: 2 | G59: 122 | H59: 199
A60: 37734 | B60: 0.64464286 | C60: 26 | E60: - КРАСНЫЙ | F60: 2 | G60: 122 | H60: 199
A61: 37735 | B61: 0.64464286 | C61: 26 | E61: - ВИННЫЙ | F61: 2 | G61: 122 | H61: 199
A62: 37736 | B62: 0.64464286 | C62: 26 | E62: - СЛИВОВЫЙ | F62: 2 | G62: 122 | H62: 199
A63: 37737 | B63: 0.64464286 | C63: 26 | E63: - ШОКОЛАДНЫЙ | F63: 2 | G63: 122 | H63: 199
A64: 38789 | B64: 0.45869565 | C64: 50 | E64: АДАПТИВНЫЙ БЛЕСК ДЛЯ ГУБ ONCOLOUR - ИДЕАЛЬНЫЙ РОЗОВЫЙ | F64: 2 | G64: 153 | H64: 249
A65: 38948 | B65: 0.53888889 | C65: 50 | E65: МАТОВАЯ ПОМАДА ONCOLOUR - МЯГКИЙ ПЕРСИК | F65: 2 | G65: 153 | H65: 249
A66: 39091 | B66: 0.53888889 | C66: 51 | E66: СИЯЮЩАЯ ГУБНАЯ ПОМАДА ONCOLOUR - СИЯЮЩИЙ ПЕРСИК | F66: 2 | G66: 153 | H66: 249
A67: 39092 | B67: 0.53888889 | C67: 51 | E67: - МЕРЦАЮЩИЙ РОЗОВЫЙ | F67: 2 | G67: 153 | H67: 249
A68: 39093 | B68: 0.53888889 | C68: 51 | E68: - ИСКРИСТЫЙ ВИШНЕВЫЙ | F68: 2 | G68: 153 | H68: 249
... A139: 48642 | B139: 0.38538462 | C139: 38 | E139: - КРАСНЫЙ | F139: 8 | G139: 491 | H139: 799
E140: ТУШЬ ДЛЯ РЕСНИЦ
A141: 38929 | B141: 0.5328125 | C141: 49 | E141: ОБЪЕМНАЯ ТУШЬ ДЛЯ РЕСНИЦ ONCOLOUR - ЧЕРНЫЙ | F141: 3 | G141: 184 | H141: 299
A142: 43123 | B142: 0.56071429 | C142: 45 | E142: ТУШЬ ДЛЯ РЕСНИЦ 5 В 1 THE ONE C ЭФФЕКТОМ HD - ЧЁРНЫЙ | F142: 3 | G142: 227 | H142: 369
A143: 46896 | B143: 0.5172043 | C143: 29 | E143: ТУШЬ ДЛЯ РЕСНИЦ С ЭФФЕКТОМ ОБЪЁМА THE ONE ЧЁРНЫЙ | F143: 4 | G143: 276 | H143: 449
A144: 47949 | B144: 0.46547619 | C144: 44 | E144: ТУШЬ ДЛЯ РЕСНИЦ 5 В 1 THE ONE.ЛИМИТИРОВАННЫЙ ВЫПУСК - ЧЁРНЫЙ | F144: 4 | G144: 276 | H144: 449
A145: 47168 | B145: 0.46547619 | C145: 44 | E145: МНОГОФУНКЦИОНАЛЬНАЯ ТУШЬ ДЛЯ РЕСНИЦ 5 В 1 THE ONE WONDERLASH XXL - ЧЁРНЫЙ | F145: 4 | G145: 276 | H145: 449
A146: 48038 | B146: 0.5172043 | C146: 43 | E146: ЦВЕТНАЯ ТУШЬ THE ONE С ЭФФЕКТОМ ГИПНОТИЧЕСКОГО ВЗГЛЯДА - ИЗЫСКАННЫЙ СИРЕНЕВЫЙ | F146: 4 | G146: 276 | H146: 449
A147: 48039 | B147: 0.5172043 | C147: 43 | E147: - ГЛУБОКИЙ БУРГУНДИ | F147: 4 | G147: 276 | H147: 449
A148: 48040 | B148: 0.5172043 | C148: 43 | E148: - НЕБЕСНЫЙ СИНИЙ | F148: 4 | G148: 276 | H148: 449
A149: 48645 | B149: 0.30083333 | C149: 31 | E149: СУПЕРТУШЬ ДЛЯ РЕСНИЦ GIORDANI GOLD. ЛИМИТИРОВАННЫЙ ВЫПУСК | F149: 8 | G149: 516 | H149: 839
E150: КАРАНДАШИ ДЛЯ ГЛАЗ И БРОВЕЙ, ПОДВОДКА ДЛЯ ГЛАЗ, ПОМАДА И ТЕНИ ДЛЯ БРОВЕЙ
A151: 43206 | B151: 0.49578947 | C151: 41 | E151: ТУШЬ ДЛЯ БРОВЕЙ THE ONE - КОРИЧНЕВЫЙ | F151: 4 | G151: 294 | H151: 479
A152: 43207 | B152: 0.49578947 | C152: 41 | E152: - ТЁМНО-КОРИЧНЕВЫЙ | F152: 4 | G152: 294 | H152: 479
A153: 47481 | B153: 0.44638554 | C153: 41 | E153: ПУДРОВЫЕ ТЕНИ ДЛЯ БРОВЕЙ THE ONE - СВЕТЛЫЙ КОРИЧНЕВЫЙ | F153: 9 | G153: 564 | H153: 919
A154: 47482 | B154: 0.44638554 | C154: 41 | E154: - СРЕДНИЙ КОРИЧНЕВЫЙ | F154: 9 | G154: 564 | H154: 919
A155: 47704 | B155: 0.64464286 | C155: 27 | E155: КАРАНДАШ-ПОДВОДКА ДЛЯ ГЛАЗ THE ONE - ЧЁРНЫЙ | F155: 2 | G155: 122 | H155: 199
A156: 47705 | B156: 0.64464286 | C156: 27 | E156: - СЕРЫЙ | F156: 2 | G156: 122 | H156: 199
A157: 47706 | B157: 0.64464286 | C157: 27 | E157: - ГОЛУБОЙ | F157: 2 | G157: 122 | H157: 199
A158: 47707 | B158: 0.64464286 | C158: 27 | E158: - КОРИЧНЕВЫЙ | F158: 2 | G158: 122 | H158: 199
A159: 47708 | B159: 0.64464286 | C159: 27 | E159: - ИЗУМРУДНЫЙ | F159: 2 | G159: 122 | H159: 199
E160: ТЕНИ ДЛЯ ВЕК
A161: 43347 | B161: 0.46516129 | C161: 42 | E161: ТЕНИ-ПОДВОДКА ДЛЯ ВЕК THE ONE COLOUR UNLIMITED - ЗЕЛЁНЫЙ ИЗУМРУД | F161: 8 | G161: 509 | H161: 829
A162: 43348 | B162: 0.46516129 | C162: 42 | E162: - ИГРИСТЫЙ НЮД | F162: 8 | G162: 509 | H162: 829
A163: 43350 | B163: 0.46516129 | C163: 42 | E163: - РОЗОВЫЙ ЗАКАТ | F163: 8 | G163: 509 | H163: 829
A164: 46351 | B164: 0.46516129 | C164: 42 | E164: СТОЙКИЕ ТЕНИ-ПОДВОДКА ДЛЯ ВЕК THE ONE COLOUR UNLIMITED - БЕЗУПРЕЧНЫЙ ПЕРСИК | F164: 8 | G164: 509 | H164: 829
A165: 46352 | B165: 0.46516129 | C165: 42 | E165: - БРОНЗОВЫЙ ПЕСОК | F165: 8 | G165: 509 | H165: 829
A166: 46353 | B166: 0.46516129 | C166: 42 | E166: - СЕРЫЙ ГРАНИТ | F166: 8 | G166: 509 | H166: 829
A167: 47604 | B167: 0.450625 | C167: 48 | E167: ПАЛЕТКА ТЕНЕЙ ДЛЯ ВЕК ONCOLOUR | F167: 8 | G167: 540 | H167: 879
E168: ТОНАЛЬНЫЕ ОСНОВЫ, РУМЯНА, ПУДРЫ, КОНСИЛЛЕРЫ
A169: 34647 | B169: 0.53 | C169: 37 | E169: КОМПАКТНАЯ МАТИРУЮЩАЯ ПУДРА THE ONE EVERLASTING - СВЕТЛЫЙ | F169: 8 | G169: 491 | H169: 799
A170: 34648 | B170: 0.53 | C170: 37 | E170: - СРЕДНИЙ | F170: 8 | G170: 491 | H170: 799
A171: 34649 | B171: 0.53 | C171: 37 | E171: - ТЁМНЫЙ | F171: 8 | G171: 491 | H171: 799
A172: 41107 | B172: 0.445 | C172: 32 | E172: КОНСИЛЕР С ПРЕБИОТИЧЕСКОЙ СЫВОРОТКОЙ GIORDANI GOLD - СВЕТЛЫЙ | F172: 9 | G172: 614 | H172: 999
A173: 41108 | B173: 0.445 | C173: 32 | E173: - СРЕДНИЙ | F173: 9 | G173: 614 | H173: 999
...

Sheet 05 КАТАЛОГ`26 (2)
A1: ПРОБНИК | B1: ПРОДУКТ | C1: ТЕСТЕРЫ | D1: ЦЕНА
A2: 11037 | B2: 42490 | C2: ТУАЛЕТНАЯ ВОДА ASCENDANT | D2: 40
A3: 11365 | B3: 42495 | C3: ПАРФЮМЕРНАЯ ВОДА AMBER ELIXIR | D3: 40
A4: 22443 | B4: 42751 | C4: ПАРФЮМИРОВАННАЯ ВОДА LOVE POTION | D4: 40
A5: 30129 | B5: 42507 | C5: ТУАЛЕТНАЯ ВОДА ECLAT FEMME | D5: 40
A6: 30557 | B6: 30468 | C6: ТУАЛЕТНОЙ ВОДЫ BE THE LEGEND | D6: 40
A7: 30885 | B7: 42519 | C7: ПАРФЮМЕРНАЯ ВОДА POSSESS | D7: 40
A8: 31817 | B8: 47511 | C8: ПАРФЮМИРОВАННАЯ ВОДА GIORDANI GOLD ESSENZA | D8: 40
A9: 33649 | B9: 33650 | C9: ПАРФЮМЕРНАЯ ВОДА POSSESS THE SECRET MAN | D9: 40
A10: 35656 | B10: 37766 | C10: ТУАЛЕТНАЯ ВОДА JOYCE ROSE | D10: 40
A11: 35666 | B11: 35665 | C11: ТУАЛЕТНАЯ ВОДА GLACIER | D11: 40
A12: 38548 | B12: 43122 | C12: ЖЕНСКАЯ ПАРФЮМЕРНАЯ ВОДА NORDIC WATERS | D12: 40
A13: 40722 | B13: 40667 | C13: ТУАЛЕТНАЯ ВОДА GLACIER EXTREME | D13: 40
A14: 41185 | B14: 40794 | C14: ДНЕВНОЙ КРЕМ-КОМФОРТ NOVAGE SKINRELIEF PRO RESILIENT SPF 30 | D14: 40
A15: 41771 | B15: 42785 | C15: ТУАЛЕТНАЯ ВОДА LUCIA | D15: 40
A16: 43937 | B16: 38538 | C16: ПАРФЮМЕРНАЯ ВОДА GIORDANI GOLD MAN | D16: 40
A17: 44289 | B17: 44288 | C17: ТУАЛЕТНАЯ ВОДА OH! SWEET DULCE DE LECHE | D17: 40
A18: 44306 | B18: 44300 | C18: ПАРФЮМИРОВАННАЯ ВОДА LOVE POTION SENSUAL RUBY | D18: 40
A19: 44847 | B19: 42101 | C19: СТОЙКАЯ МИНЕРАЛЬНАЯ ТОНАЛЬНАЯ ОСНОВА GIORDANI GOLD - НЕЙТРАЛЬНЫЙ ВАНИЛЬНЫЙ | D19: 40
A20: 44853 | B20: 42107 | C20: - ЕСТЕСТВЕННЫЙ БЕЖЕВЫЙ | D20: 40
A21: 44857 | B21: 42653 | C21: - РОСКОШНАЯ ОРХИДЕЯ | D21: 40
A22: 44862 | B22: 42658 | C22: - БЕЗУПРЕЧНЫЙ РОЗОВЫЙ | D22: 40
A23: 44865 | B23: 42112 | C23: МУЛЬТИФУНКЦИОНАЛЬНЫЙ СС-КРЕМ GG SPF 30 - СВЕТЛЫЙ | D23: 40
A24: 44866 | B24: 42113 | C24: - ЕСТЕСТВЕННЫЙ | D24: 40
A25: 44871 | B25: 42236 | C25: АНТИВОЗРАСТНАЯ ТОН. ОСНОВА С ПРЕБИОТИЧЕСКОЙ СЫВОРОТКОЙ GIORDANI GOLD - СЛОНОВАЯ КОСТЬ (НЕЙТРАЛЬНЫЙ) | D25: 55
A26: 44872 | B26: 42236 | C26: АНТИВОЗРАСТНАЯ ТОН. ОСНОВА С ПРЕБИОТИЧЕСКОЙ СЫВОРОТКОЙ GIORDANI GOLD - БЕЖЕВЫЙ (ТЁПЛЫЙ) | D26: 55
A27: 45395 | B27: 38497 | C27: ПАРФЮМЕРНАЯ ВОДА DIVINE | D27: 40
A28: 45636 | B28: 43244 | C28: СИЯЮЩАЯ ТОНАЛЬНАЯ ОСНОВА GIORDANI GOLD SPF 25 - ТЁПЛЫЙ ФАРФОРОВЫЙ | D28: 40
A29: 45637 | B29: 43245 | C29: - НЕЙТРАЛЬНЫЙ БЕЖ | D29: 40
A30: 45639 | B30: 43247 | C30: - СЛОНОВАЯ КОСТЬ | D30: 40
A31: 45696 | B31: 41365 | C31: ДНЕВНОЙ КРЕМ WAUNT «ДЗЕН-ЭФФЕКТ» | D31: 40
A32: 45880 | B32: 44308 | C32: ТУАЛЕТНАЯ ВОДА VENTURE POWER | D32: 40
A33: 45891 | B33: 45890 | C33: ТУАЛЕТНАЯ ВОДА EXCITE FOR HIM | D33: 40
A34: 46054 | B34: 46052 | C34: ПАРФЮМЕРНАЯ ВОДА VOLARE TENDER | D34: 40
A35: 46055 | B35: 45967 | C35: МУЖСКИЕ ДУХИ GIORDANI GOLD ESSENZA MAN | D35: 40
A36: 46106 | B36: 45138 | C36: КРЕМ ДЛЯ ЛИЦА WELLOSOPHY-РАЗГЛАЖИВАНИЕ И ОБНОВЛЕНИЕ | D36: 40
A37: 46107 | B37: 45139 | C37: ГЕЛЬ-СЫВОРОТКА ДЛЯ ЛИЦА WELLOSOPHY-ОМОЛОЖЕНИЕ И ВОССТАНОВЛЕНИЕ | D37: 40
A38: 46335 | B38: 46329 | C38: ТОНАЛЬНАЯ ОСНОВА С ЭФФЕКТОМ СИЯНИЯ THE ONE - ВАНИЛЬНЫЙ | D38: 55
A39: 46340 | B39: 46333 | C39: - БЕЖЕВЫЙ НЕЙТРАЛЬНЫЙ | D39: 55
A40: 46606 | B40: 46064 | C40: МУЖСКАЯ ПАРФЮМЕРНАЯ ВОДА NORDIC WATERS INFINITE BLUE | D40: 40
A41: 46665 | B41: 46648 | C41: ЖЕНСКАЯ ПАРФЮМЕРНАЯ ВОДА NORDIC WATERS INFINITE BLUE | D41: 40
A42: 46735 | B42: 46718 | C42: ПАРФЮМЕРНАЯ ВОДА MISS GIORDANI FLORAL | D42: 40
A43: 47129 | B43: 46906 | C43: ТОНАЛЬНАЯ ОСНОВА-АНТИСТРЕСС THE ONE - СВЕТЛЫЙ БЕЖ | D43: 40
A44: 47130 | B44: 46906 | C44: - ТЁПЛЫЙ БЕЖ | D44: 40
A45: 47501 | B45: 47498 | C45: ТУАЛЕТНАЯ ВОДА EVERY ME DRAMA QUEEN IRIS | D45: 40
A46: 47503 | B46: 47499 | C46: ТУАЛЕТНАЯ ВОДА MIDNIGHT MAGIC ELVIE | D46: 40
A47: 47516 | B47: 46795 | C47: ТУАЛЕТНАЯ ВОДА ECLAT HOMME WEEKEND AZUR | D47: 40
A48: 47571 | B48: 45291 | C48: КРЕМ ДЛЯ КОНТУРА ГЛАЗ И ГУБ OPTIMALS | D48: 40
A49: 47572 | B49: 45326 | C49: УНИВЕРСАЛЬНЫЙ КРЕМ ДЛЯ ЛИЦА 10 В 1 OPTIMALS | D49: 40
A50: 47610 | B50: 46435 | C50: КРЕМОВАЯ ГУБНАЯ ПОМАДА THE ONE SMART SYNC - РУМЯНЫЙ НЮД | D50: 40
A51: 47612 | B51: 46437 | C51: - ТЁПЛОЕ КАКАО | D51: 40
A52: 47615 | B52: 46440 | C52: - НЕЖНЫЙ РОЗОВЫЙ | D52: 40
A53: 47617 | B53: 46442 | C53: - МЯГКИЙ ПУРПУРНЫЙ | D53: 40
A54: 47618 | B54: 46443 | C54: - ГОРЯЧЕЕ МОККО | D54: 40
A55: 47619 | B55: 46444 | C55: - СЛАДКИЙ ШОКОЛАД | D55: 40
A56: 47620 | B56: 46445 | C56: - КРЕПКИЙ ЭСПРЕССО | D56: 40
A57: 47621 | B57: 46446 | C57: - НАСЫЩЕННЫЙ ЯГОДНЫЙ | D57: 40
A58: 47622 | B58: 46447 | C58: - КЛАССИЧЕСКИЙ КРАСНЫЙ | D58: 40
A59: 48660 | B59: 45243 | C59: ЛЁГКИЙ КРЕМ ДЛЯ ЛИЦА ПРОТИВ ПИГМЕНТАЦИИ OPTIMALS EVEN OUT | D59: 40
A60: 48660 | B60: 45243 | C60: ЛЁГКИЙ КРЕМ ДЛЯ ЛИЦА ПРОТИВ ПИГМЕНТАЦИИ OPTIMALS EVEN OUT | D60: 40
A61: 48661 | B61: 45245 | C61: НАСЫЩЕННЫЙ КРЕМ ДЛЯ ЛИЦА ПРОТИВ ПИГМЕНТАЦИИ OPTIMALS EVEN OUT | D61: 40
A62: 48661 | B62: 45245 | C62: НАСЫЩЕННЫЙ КРЕМ ДЛЯ ЛИЦА ПРОТИВ ПИГМЕНТАЦИИ OPTIMALS EVEN OUT | D62: 40
A63: 48662 | B63: 45248 | C63: СЫВОРОТКА ДЛЯ ЛИЦА ПРОТИВ ПИГМЕНТАЦИИ OPTIMALS EVEN OUT | D63: 40
A64: 48662 | B64: 45248 | C64: СЫВОРОТКА ДЛЯ ЛИЦА ПРОТИВ ПИГМЕНТАЦИИ OPTIMALS EVEN OUT | D64: 40
A65: 34145 | B65: 42520 | C65: ТУАЛЕТНАЯ ВОДА LUCIA BRIGHT AURA | D65: 40
A66: 35652 | B66: 35651 | C66: ТУАЛЕТНАЯ ВОДА ДЛЯ НЕГО ECLAT TOUJOURS | D66: 40
A67: 35654 | B67: 35653 | C67: ПАРФЮМЕРНАЯ ВОДА INFINITA | D67: 40
A68: 38546 | B68: 38550 | C68: МУЖСКАЯ ПАРФЮМЕРНАЯ ВОДА NORDIC WATERS | D68: 40
A69: 41163 | B69: 35679 | C69: ДУХИ ALL OR NOTHING | D69: 40
A70: 43938 | B70: 38531 | C70: ПАРФЮМЕРНАЯ ВОДА GIORDANI GOLD WOMAN | D70: 40
A71: 44316 | B71: 44315 | C71: ПАРФЮМЕРНАЯ ВОДА INFINITA MY SUNSHINE | D71: 40
A72: 45366 | B72: 45357 | C72: ПАРФЮМЕРНАЯ ВОДА POSSESS ABSOLUTE MAN | D72: 40
A73: 46802 | B73: 47713 | C73: ПАРФЮМЕРНАЯ ВОДА INFINITA YOU | D73: 40
A74: 47206 | B74: 46793 | C74: ТУАЛЕТНАЯ ВОДА EVERY ME SWEETHEART ROSE | D74: 40
A75: 548052 | C75: НАБОР ПРОБНИКОВ NOVAGE 3.0 LIFTING | D75: 200
A76: 548052 | C76: НАБОР ПРОБНИКОВ NOVAGE 3.0 LIFTING | D76: 695
A77: 548053 | C77: НАБОР ПРОБНИКОВ NOVAGE 3.0 BRIGHTENING | D77: 200
A78: 548053 | C78: НАБОР ПРОБНИКОВ NOVAGE 3.0 BRIGHTENING | D78: 695
A79: 548054 | C79: НАБОР ПРОБНИКОВ NOVAGE 3.0 ANTI-ACNE | D79: 200
A80: 548054 | C80: НАБОР ПРОБНИКОВ NOVAGE 3.0 ANTI-ACNE | D80: 695
A81: 548260 | C81: НАБОР ПРОБНИКОВ NOVAGE+ RESTORE | D81: 200
A82: 548260 | C82: НАБОР ПРОБНИКОВ NOVAGE+ RESTORE | D82: 695
A83: 548268 | C83: НАБОР ПРОБНИКОВ NOVAGE 3.0 WRINKLE | D83: 200
A84: 548268 | C84: НАБОР ПРОБНИКОВ NOVAGE 3.0 WRINKLE | D84: 695
A86: Один каталог следующего периода автоматически вкладывается в первый балловый заказ текущего периода по специальной цене 41 рубля
B88: код | C88: наименование | D88: 1 каталог, руб.
B89: 507006 | C89: КАТАЛОГ №06 2026 (20.04.2026 - 09.05.2026) | D89: 75
A91: Дополнительно ты можешь приобрести следующие наборы каталогов Oriflame:
B93: код | C93: наименование | D93: цена, руб.
B94: 546430 | C94: Набор из 3 каталогов следующего периода | D94: 183
B95: 546420 | C95: Набор из 10 каталогов следующего периода | D95: 445
B96: 546425 | C96: Набор из 25 каталогов следующего периода | D96: 1045
B99: код | C99: наименование | D99: 1 шт.
B100: 526447 | C100: Средний бумажный пакет | D100: 19
B101: 526448 | C101: Маленький бумажный пакет | D101: 16

Sheet 05 КАТАЛОГ`26 (3)
B1: ПРОДУКЦИЯ, НЕ ПРЕДСТАВЛЕННАЯ В КАТАЛОГЕ
A2: КОД | B2: НАИМЕНОВАНИЕ | C2: ББ | D2: ОП | E2: ПЦ
B3: ПОМАДЫ, БЛЕСКИ И КАРАНДАШИ ДЛЯ ГУБ
A4: 37731 | B4: КАРАНДАШ ДЛЯ ГУБ THE ONE - РОЗОВЫЙ | C4: 5 | D4: 344 | E4: 560
B5: АРОМАТЫ
A6: 37772 | B6: ТУАЛЕТНАЯ ВОДА JOYCE JADE | C6: 16 | D6: 1045 | E6: 1700
A7: 42828 | B7: ТУАЛЕТНАЯ ВОДА WOMEN'S COLLECTION CHERRY BLOSSOM | C7: 21 | D7: 1383 | E7: 2250
A8: 44288 | B8: ТУАЛЕТНАЯ ВОДА OH! SWEET DULCE DE LECHE | C8: 21 | D8: 1383 | E8: 2250
A9: 33958 | B9: ПАРФЮМИРОВАННЫЙ СПРЕЙ ДЛЯ ТЕЛА LOVE POTION SO TEMPTING | C9: 15 | D9: 983 | E9: 1600
A10: 38526 | B10: ПАРФЮМИРОВАННЫЙ СПРЕЙ ДЛЯ ТЕЛА LOVE POTION BLOSSOM KISS | C10: 15 | D10: 983 | E10: 1600
A11: 42518 | B11: ТУАЛЕТНАЯ ВОДА MEN'S COLLECTION DARK WOOD | C11: 21 | D11: 1383 | E11: 2250
B12: УХОД ДЛЯ ТЕЛА
A13: 12760 | B13: СПЕЦИАЛЬНОЕ СМЯГЧАЮЩЕЕ СРЕДСТВО | C13: 4 | D13: 246 | E13: 400
A14: 34499 | B14: УСПОКАИВАЮЩИЙ ГЕЛЬ ДЛЯ ИНТИМНОЙ ГИГИЕНЫ FEMINELLE | C14: 7 | D14: 461 | E14: 750
A15: 34500 | B15: ОСВЕЖАЮЩИЙ ГЕЛЬ ДЛЯ ИНТИМНОЙ ГИГИЕНЫ FEMINELLE | C15: 7 | D15: 461 | E15: 750
A16: 34504 | B16: СМЯГЧАЮЩИЙ КРЕМ-ГЕЛЬ ДЛЯ ИНТИМНОЙ ГИГИЕНЫ FEMINELLE | C16: 7 | D16: 461 | E16: 750
A17: 39377 | B17: ОСВЕЖАЮЩИЙ ГЕЛЬ ДЛЯ ДУША С ОКЕАНСКИМ АККОРДОМ SCENTS & MOMENTS | C17: 4 | D17: 246 | E17: 400
A18: 39389 | B18: РАССЛАБЛЯЮЩИЙ ГЕЛЬ ДЛЯ ДУША С ЛАВАНДОЙ SCENTS & MOMENTS | C18: 4 | D18: 246 | E18: 400
A19: 39399 | B19: ЧУВСТВЕННЫЙ ГЕЛЬ ДЛЯ ДУША С ПИОНОМ SCENTS & MOMENTS | C19: 4 | D19: 246 | E19: 400
A20: 39426 | B20: БОДРЯЩИЙ ГЕЛЬ ДЛЯ ДУША С РОЗОВЫМ ГРЕЙПФРУТОМ SCENTS & MOMENTS | C20: 4 | D20: 246 | E20: 400
A21: 41264 | B21: БОДРЯЩИЙ ГЕЛЬ ДЛЯ ДУША С ОРГАНИЧЕСКОЙ КОКОСОВОЙ ВОДОЙ И ДЫНЕЙ LOVE NATURE | C21: 5 | D21: 295 | E21: 480
A22: 41265 | B22: БОДРЯЩИЙ ГЕЛЬ ДЛЯ ДУША LOVE NATURE. БОЛЬШОЙ ОБЪЁМ | C22: 8 | D22: 522 | E22: 850
A23: 41280 | B23: ОСВЕЖАЮЩИЙ ГЕЛЬ ДЛЯ ДУША С ЗЕЛЁНЫМ ЧАЕМ И ОГУРЦОМ LOVE NATURE | C23: 5 | D23: 295 | E23: 480
A24: 41283 | B24: ПИТАТЕЛЬНОЕ МАСЛО ДЛЯ ТЕЛА, ЛИЦА И ВОЛОС С ОРГАНИЧЕСКИМ АВОКАДО LOVE NATURE | C24: 13 | D24: 817 | E24: 1330
... A40: 48548 | B40: ГУБКА ДЛЯ ДУША | C40: 3 | D40: 86 | E40: 279
B41: ДЕЗОДОРАНТЫ
A42: 33144 | B42: СПРЕЙ ДЕЗОДОРАНТ С УХАЖИВАЮЩИМ КОМПЛЕКСОМ ACTIVELLE | C42: 6 | D42: 399 | E42: 650
A43: 33147 | B43: СПРЕЙ ДЕЗОДОРАНТ ДЛЯ ЭКСТРЕМАЛЬНОЙ ЗАЩИТЫ ACTIVELLE | C43: 6 | D43: 399 | E43: 650
A44: 41311 | B44: СПРЕЙ ДЕЗОДОРАНТ БЕЗ БЕЛЫХ СЛЕДОВ ACTIVELLE | C44: 6 | D44: 399 | E44: 650
A45: 43927 | B45: ШАРИКОВЫЙ ДЕЗОДОРАНТ NORTH FOR MEN ULTIMATE BALANCE | C45: 5 | D45: 326 | E45: 530
A46: 46382 | B46: СПРЕЙ ДЕЗОДОРАНТ-АНТИПЕРСПИРАНТ ДЛЯ МАКСИМАЛЬНОЙ СВЕЖЕСТИ ACTIVELLE | C46: 6 | D46: 399 | E46: 650
B47: УХОД ДЛЯ РУК
A48: 41335 | B48: КРЕМ ДЛЯ РУК И НОГТЕЙ С ОРГАНИЧЕСКИМ МАСЛОМ МАКАДАМИИ LOVE NATURE | C48: 4 | D48: 264 | E48: 430
A49: 41341 | B49: КРЕМ ДЛЯ РУК С ОРГАНИЧЕСКИМ РОЗОВЫМ ГРЕЙПФРУТОМ LOVE NATURE | C49: 4 | D49: 264 | E49: 430
A50: 46219 | B50: МИНИ-КРЕМ ДЛЯ РУК | C50: 2 | D50: 135 | E50: 220
A51: 47536 | B51: КРЕМ ДЛЯ РУК И ТЕЛА MILK & HONEY GOLD - МАГНОЛИЯ | C51: 9 | D51: 615 | E51: 1000
A52: 47537 | B52: ЖИДКОЕ МЫЛО ДЛЯ РУК И ТЕЛА MILK & HONEY GOLD - МАГНОЛИЯ | C52: 8 | D52: 522 | E52: 850
A53: 46979 | B53: ПАРФЮМИРОВАННЫЙ КРЕМ ДЛЯ РУК LOVE POTION CHERRY ON TOP | C53: 6 | D53: 363 | E53: 590
A54: 47202 | B54: ЗАЩИТНЫЙ КРЕМ ДЛЯ РУК И НОГТЕЙ С ОРГАНИЧЕСКИМ ЭКСТРАКТОМ МАРАКУЙИ LOVE NATURE | C54: 4 | D54: 264 | E54: 430
A55: 46621 | B55: ЛОСЬОН ДЛЯ РУК И ТЕЛА NEON VIBES | C55: 9 | D55: 615 | E55: 1000
A56: 47275 | B56: КРЕМ ДЛЯ РУК И ТЕЛА С ОРГАНИЧЕСКОЙ ТЫКВОЙ И КОРИЦЕЙ LOVE NATURE | C56: 8 | D56: 510 | E56: 830
B57: УХОД ДЛЯ НОГ
A58: 38336 | B58: ГЕЛЕВЫЕ НАКЛЕЙКИ ДЛЯ ОБУВИ | C58: 4 | D58: 138 | E58: 450
A59: 41247 | B59: ГЕЛЕВЫЕ ПОДУШЕЧКИ ДЛЯ ЗАДНИКОВ ОБУВИ | C59: 5 | D59: 175 | E59: 570
A60: 41249 | B60: ПОДУШЕЧКИ ДЛЯ ОБУВИ | C60: 5 | D60: 175 | E60: 570
A61: 46981 | B61: СЫВОРОТКА-РАЗМЯГЧИТЕЛЬ МОЗОЛЕЙ И НАТОПТЫШЕЙ FEET UP EXPERT | C61: 9 | D61: 603 | E61: 980
A62: 46982 | B62: ДЕЗОДОРАНТ-АНТИПЕРСПИРАНТ ДЛЯ НОГ FEET UP EXPERT | C62: 13 | D62: 861 | E62: 1400
A63: 46983 | B63: ИНТЕНСИВНО УВЛАЖНЯЮЩАЯ МАСКА ДЛЯ НОГ FEET UP EXPERT | C63: 11 | D63: 688 | E63: 1120
A64: 47671 | B64: ПИЛКА ДЛЯ НОГ 4 В 1 | C64: 6 | D64: 212 | E64: 690
A65: 47423 | B65: КУСАЧКИ ДЛЯ НОГТЕЙ | C65: 5 | D65: 154 | E65: 500
A66: 47426 | B66: ШЛИФОВАЛЬНАЯ ПИЛКА ДЛЯ НОГ | C66: 4 | D66: 138 | E66: 450
A67: 47427 | B67: ШЛИФОВАЛЬНАЯ ПИЛКА ДЛЯ НОГ | C67: 6 | D67: 200 | E67: 650
A68: 47428 | B68: ИНСТРУМЕНТ ДЛЯ УДАЛЕНИЯ МОЗОЛЕЙ | C68: 8 | D68: 258 | E68: 840
A69: 47429 | B69: ТЁРКА ДЛЯ НОГ | C69: 6 | D69: 200 | E69: 650
... A71: 46636 | B71: ПИТАТЕЛЬНЫЙ КРЕМ ДЛЯ НОГ С ЭКСТРАКТОМ СЛИВЫ И МАСЛОМ ШИ FEET UP | C71: 6 | D71: 387 | E71: 630
B72: УХОД ДЛЯ ТЕЛА
A73: 48960 | B73: МЫЛО С АРОМАТОМ ЛЕСНОЙ СВЕЖЕСТИ SCENTS & MOMENTS «ТАИНСТВЕННЫЙ ЛЕС» | C73: 2 | D73: 129 | E73: 210
A74: 48961 | B74: МЫЛО С ЦИТРУСОВЫМ АРОМАТОМ SCENTS & MOMENTS «ЦИТРУСОВЫЙ МИКС» | C74: 2 | D74: 129 | E74: 210
A75: 48965 | B75: МЫЛО С АКВАТИЧЕСКИМ АРОМАТОМ SCENTS & MOMENTS «ГОРНОЕ ОЗЕРО» | C75: 2 | D75: 129 | E75: 210
A76: 48981 | B76: СИЛИКОНОВАЯ МОЧАЛКА ДЛЯ ДУША | C76: 9 | D76: 307 | E76: 1000
A77: 47013 | B77: ПАРФЮМИРОВАННЫЙ КРЕМ ДЛЯ ТЕЛА LOVE POTION | C77: 13 | D77: 817 | E77: 1330
A78: 47538 | B78: МЫЛО MILK & HONEY GOLD - МАГНОЛИЯ | C78: 3 | D78: 190 | E78: 310
A79: 47542 | B79: МАССАЖНАЯ ПЕРЧАТКА | C79: 4 | D79: 120 | E79: 390
A80: 47878 | B80: ГУБКА ДЛЯ ДУША | C80: 4 | D80: 122 | E80: 399
B81: УХОД ДЛЯ ВОЛОС
A82: 38601 | B82: ЗАЩИТНОЕ МАСЛО ДЛЯ ВОЛОС ELEO | C82: 20 | D82: 1291 | E82: 2100
A83: 38602 | B83: НОЧНОЕ ВОССТАНАВЛИВАЮЩЕЕ МАСЛО-ЭЛИКСИР ДЛЯ ВОЛОС ELEO | C83: 20 | D83: 1291 | E83: 2100
A84: 41292 | B84: ШАМПУНЬ ДЛЯ СУХИХ ВОЛОС С ОРГАНИЧЕСКОЙ ПШЕНИЦЕЙ И КОКОСОМ LOVE NATURE | C84: 8 | D84: 522 | E84: 850
A85: 41295 | B85: ПИТАТЕЛЬНЫЙ КОНДИЦИОНЕР ДЛЯ СУХИХ ВОЛОС С ОРГАНИЧЕСКОЙ ПШЕНИЦЕЙ И КОКОСОМ LOVE NATURE | C85: 8 | D85: 522 | E85: 850
A86: 44950 | B86: ШАМПУНЬ ДЛЯ ИНТЕНСИВНОГО ВОССТАНОВЛЕНИЯ ВОЛОС DUOLOGI | C86: 10 | D86: 646 | E86: 1050
A87: 44951 | B87: ШАМПУНЬ ПРОТИВ ПЕРХОТИ DUOLOGI | C87: 10 | D87: 646 | E87: 1050
A88: 44956 | B88: ШАМПУНЬ ДЛЯ ЗАЩИТЫ ЦВЕТА DUOLOGI | C88: 10 | D88: 646 | E88: 1050
A89: 44963 | B89: МАСКА ДЛЯ ИНТЕНСИВНОГО ВОССТАНОВЛЕНИЯ ВОЛОС DUOLOGI | C89: 14 | D89: 892 | E89: 1450
A90: 44964 | B90: ВОССТАНАВЛИВАЮЩАЯ СЫВОРОТКА ДЛЯ СЕКУЩИХСЯ ВОЛОС DUOLOGI | C90: 13 | D90: 861 | E90: 1400
A91: 44967 | B91: ТОНИК ДЛЯ КОЖИ ГОЛОВЫ ПРОТИВ ВЫПАДЕНИЯ ВОЛОС DUOLOGI | C91: 13 | D91: 861 | E91: 1400
A92: 44968 | B92: МУЛЬТИФУНКЦИОНАЛЬНЫЙ СС-СПРЕЙ ДЛЯ ВОЛОС DUOLOGI | C92: 13 | D92: 861 | E92: 1400
A93: 45436 | B93: КРЕМ ДЛЯ ФОРМИРОВАНИЯ ЛОКОНОВ DUOLOGI | C93: 12 | D93: 769 | E93: 1250
... A101: 47877 | B101: ЩЁТКА ДЛЯ РАСПУТЫВАНИЯ ВОЛОС | C101: 7 | D101: 215 | E101: 699
B102: УХОД ДЛЯ ЛИЦА
A103: 21339 | B103: МИЦЕЛЛЯРНЫЙ ОЧИЩАЮЩИЙ ЛОСЬОН DIAMOND CELLULAR | C103: 17 | D103: 1106 | E103: 1800
A104: 34843 | B104: СУЖАЮЩИЙ ПОРЫ ТОНИК ДЛЯ ЛИЦА LOVE NATURE | C104: 6 | D104: 394 | E104: 640
A105: 34845 | B105: МАТИРУЮЩИЙ КРЕМ-ФЛЮИД ДЛЯ ЛИЦА LOVE NATURE | C105: 6 | D105: 394 | E105: 640
A106: 35576 | B106: ОЧИЩАЮЩАЯ МАСКА-СКРАБ 2-В-1 ДЛЯ ЛИЦА С ОРГАНИЧЕСКИМ ЧАЙНЫМ ДЕРЕВОМ И ЛАЙМОМ LOVE NATURE | C106: 6 | D106: 394 | E106: 640
A107: 35767 | B107: УНИВЕРСАЛЬНЫЙ УВЛАЖНЯЮЩИЙ КРЕМ ДЛЯ ЛИЦА И ТЕЛА ESSENTIALS | C107: 8 | D107: 510 | E107: 830
A108: 41671 | B108: СРЕДСТВО ДЛЯ УМЫВАНИЯ PURE SKIN | C108: 9 | D108: 584 | E108: 950
A109: 41672 | B109: ОЧИЩАЮЩИЙ ТОНИК PURE SKIN | C109: 9 | D109: 584 | E109: 950
A110: 41674 | B110: МАСКА ДЛЯ ЛИЦА С ГЛИНОЙ PURE SKIN | C110: 7 | D110: 461 | E110: 750
A111: 42263 | B111: УВЛАЖНЯЮЩАЯ ЭССЕНЦИЯ-СПРЕЙ ДЛЯ ЛИЦА NOVAGE+ PROCEUTICALS | C111: 20 | D111: 1291 | E111: 2100
A112: 42615 | B112: ОЧИЩАЮЩАЯ ГЛИНЯНАЯ МАСКА ДЛЯ ВСЕХ ТИПОВ КОЖИ OPTIMALS | C112: 11 | D112: 707 | E112: 1150
A113: 43906 | B113: ВЫРАВНИВАЮЩИЙ КРЕМ ДЛЯ ЛИЦА С SPF 10 GLOW ESSENTIALS | C113: 5 | D113: 332 | E113: 540
A114: 43908 | B114: ОЧИЩАЮЩЕЕ СРЕДСТВО ДЛЯ ЛИЦА 3 В 1 GLOW ESSENTIALS | C114: 5 | D114: 332 | E114: 540
... A132: 47519 | B132: ДВУСТОРОННЯЯ ЩЁТКА ДЛЯ ОЧИЩЕНИЯ ЛИЦА | C132: 9 | D132: 286 | E132: 930
B133: КИСТИ, СПОНЖИ, ПИНЦЕТЫ, ТОЧИЛКИ, ЩИПЧИКИ
A134: 47521 | B134: СПОНЖ КОННЯКУ | C134: 10 | D134: 323 | E134: 1050
A135: 47522 | B135: СПОНЖ КОННЯКУ С УГЛЁМ | C135: 10 | D135: 323 | E135: 1050
A136: 47530 | B136: ПИНЦЕТ ДЛЯ УДАЛЕНИЯ ЧЁРНЫХ ТОЧЕК | C136: 6 | D136: 200 | E136: 650
A137: 47822 | B137: ДВУСТОРОННЯЯ КИСТЬ ДЛЯ МАКИЯЖА | C137: 12 | D137: 399 | E137: 1300
A138: 47823 | B138: ДВУСТОРОННЯЯ КИСТЬ ДЛЯ МАКИЯЖА | C138: 12 | D138: 399 | E138: 1300
A139: 47827 | B139: ВЕЕРНАЯ КИСТЬ ДЛЯ ХАЙЛАЙТЕРА | C139: 5 | D139: 169 | E139: 550
A140: 47830 | B140: ДВУСТОРОННЯЯ КИСТЬ ДЛЯ ТЕНЕЙ | C140: 5 | D140: 169 | E140: 550
...

Sheet СПЕЦПРЕДЛОЖЕНИЯ
A1: КОД | B1: АКЦИЯ | C1: Наименование | D1: ББ | E1: ОП | F1: ПЦ
C2: предложение со стр. 8-9
A3: 46045 | B3: + | C3: МУЖСКАЯ ПАРФЮМЕРНАЯ ВОДА MISTER GIORDANI | D3: 39 | E3: 2521 | F3: 4100
A4: 47513 | B4: + | C4: ПАРФЮМЕРНАЯ ВОДА MISS GIORDANI | D4: 39 | E4: 2521 | F4: 4100
C5: ЦЕНА 1499 РУБ. ПРИ ЗАКАЗЕ НА 3000 РУБ. ИЗ ЭТОГО КАТАЛОГА ИЛИ НА САЙТЕ В ПЕРИОД ДЕЙСТВИЯ КАТАЛОГА (КРОМЕ ПРОДУКТОВ-УЧАСТНИКОВ АКЦИИ 46045, 47513, 29699, 38836, 38838, 40745, 45306, 45307, 37285, 37289, 37290) | D5: 14 | E5: 922 | F5: 1499
C6: предложение со стр. 10-11
A7: 45287 | B7: + | C7: МИЦЕЛЛЯРНАЯ ВОДА OPTIMALS | D7: 5 | E7: 356 | F7: 579
A8: 47278 | B8: + | C8: УВЛАЖНЯЮЩИЙ ТОНИК OPTIMALS | D8: 5 | E8: 356 | F8: 579
C9: ЦЕНА 299 РУБ. ПРИ ЗАКАЗЕ ЛЮБОГО СРЕДСТВА OPTIMALS СО СТР. 12-17 (КРОМЕ 45287, 47278 И ПРОБНИКОВ 48938, 48939, 48940) | D9: 3 | E9: 184 | F9: 299
C10: предложение со стр. 29
A11: 46134 | B11: + | C11: ВЫРАВНИВАЮЩИЙ BB-КРЕМ С SPF 15 THE ONE - ВАНИЛЬНЫЙ | D11: 7 | E11: 448 | F11: 729
A12: 46135 | B12: + | C12: - СВЕТЛЫЙ БЕЖ | D12: 7 | E12: 448 | F12: 729
A13: 46136 | B13: + | C13: - СЛОНОВАЯ КОСТЬ | D13: 7 | E13: 448 | F13: 729
A14: 46137 | B14: + | C14: - ТЁПЛЫЙ БЕЖ | D14: 7 | E14: 448 | F14: 729
A15: 46435 | B15: + | C15: КРЕМОВАЯ ГУБНАЯ ПОМАДА THE ONE SMART SYNC - РУМЯНЫЙ НЮД | D15: 6 | E15: 381 | F15: 619
A16: 46436 | B16: + | C16: - ЗОЛОТАЯ КАРАМЕЛЬ | D16: 6 | E16: 381 | F16: 619
A17: 46437 | B17: + | C17: - ТЁПЛОЕ КАКАО | D17: 6 | E17: 381 | F17: 619
A18: 46438 | B18: + | C18: - МЯГКИЙ ТЕРРАКОТОВЫЙ | D18: 6 | E18: 381 | F18: 619
A19: 46439 | B19: + | C19: - РОЗОВЫЙ КЛЕВЕР | D19: 6 | E19: 381 | F19: 619
A20: 46440 | B20: + | C20: - НЕЖНЫЙ РОЗОВЫЙ | D20: 6 | E20: 381 | F20: 619
A21: 46441 | B21: + | C21: - РОЗОВОЕ ДЕРЕВО | D21: 6 | E21: 381 | F21: 619
A22: 46442 | B22: + | C22: - МЯГКИЙ ПУРПУРНЫЙ | D22: 6 | E22: 381 | F22: 619
... A30: 46896 | B30: + | C30: ТУШЬ ДЛЯ РЕСНИЦ С ЭФФЕКТОМ ОБЪЁМА THE ONE ЧЁРНЫЙ | D30: 4 | E30: 276 | F30: 449
C31: ЛЮБОЙ ОТТЕНОК ВВ-КРЕМА + ЛЮБОЙ ОТТЕНОК КРЕМОВОЙ ГУБНОЙ ПОМАДЫ + ТУШЬ ДЛЯ РЕСНИЦ ЗА 1199 РУБ. | D31: 11 | E31: 739 | F31: 1199
C32: предложение со стр. 31
A33: 42112 | B33: + | C33: МУЛЬТИФУНКЦИОНАЛЬНЫЙ СС-КРЕМ GG SPF 30 - СВЕТЛЫЙ | D33: 12 | E33: 768 | F33: 1249
A34: 42113 | B34: + | C34: - ЕСТЕСТВЕННЫЙ | D34: 12 | E34: 768 | F34: 1249
A35: 44821 | B35: + | C35: ЖИДКАЯ ГУБНАЯ ПОМАДА-ЭЛИКСИР SPF 15 GIORDANI GOLD - БАРХАТНЫЙ РУМЯНЕЦ | D35: 8 | E35: 516 | F35: 839
A36: 44822 | B36: + | C36: - НЕЖНЫЙ НЮД | D36: 8 | E36: 516 | F36: 839
A37: 44823 | B37: + | C37: - МЯГКАЯ КАРАМЕЛЬ | D37: 8 | E37: 516 | F37: 839
A38: 44824 | B38: + | C38: - ПРИГЛУШЁННЫЙ КОРАЛЛ | D38: 8 | E38: 516 | F38: 839
A39: 44825 | B39: + | C39: - ПРЯНАЯ РОЗА | D39: 8 | E39: 516 | F39: 839
A40: 44826 | B40: + | C40: - ШОКОЛАДНЫЙ ВЕЛЮР | D40: 8 | E40: 516 | F40: 839
A41: 44827 | B41: + | C41: - РОЗОВОЕ ДЕРЕВО | D41: 8 | E41: 516 | F41: 839
A42: 44828 | B42: + | C42: - ВИННАЯ ЯГОДА | D42: 8 | E42: 516 | F42: 839
A43: 44829 | B43: + | C43: - РОСКОШНЫЙ АЛЫЙ | D43: 8 | E43: 516 | F43: 839
A44: 44830 | B44: + | C44: - ПЫШНАЯ ВИШНЯ | D44: 8 | E44: 516 | F44: 839
A45: 48645 | B45: + | C45: СУПЕРТУШЬ ДЛЯ РЕСНИЦ GIORDANI GOLD. ЛИМИТИРОВАННЫЙ ВЫПУСК | D45: 8 | E45: 516 | F45: 839
C46: ЛЮБОЙ ОТТЕНОК СС-КРЕМА + ЛЮБОЙ ОТТЕНОК ЖИДКОЙ ГУБНОЙ ПОМАДЫ-ЭЛИКСИРА + СУПЕРТУШЬ ДЛЯ РЕСНИЦ ЗА 1899 РУБ. | D46: 18 | E46: 1168 | F46: 1899
C47: предложение со стр. 104
A48: 45082 | B48: + | C48: ОЧИЩАЮЩАЯ ЩЁТКА ДЛЯ ЛИЦА | D48: 26 | E48: 845 | F48: 2749
C49: ЦЕНА 999 РУБ. ПРИ ЗАКАЗЕ ЛЮБОГО КОМПЛЕКСНОГО УХОДА NOVAGE ИЗ ЭТОГО КАТАЛОГА ИЛИ НА САЙТЕ В ПЕРИОД ДЕЙСТВИЯ КАТАЛОГА | D49: 9 | E49: 307 | F49: 999
C50: предложение со стр. 105
A51: 41029 | C51: ОЧИЩАЮЩИЙ ГЕЛЬ ДЛЯ ЛИЦА NOVAGE+ | D51: 17 | E51: 1137 | F51: 1850
A52: 41034 | C52: КРЕМ ДЛЯ КОЖИ ВОКРУГ ГЛАЗ ПРОТИВ МОРЩИН NOVAGE+ WRINKLE SMOOTH | D52: 28 | E52: 1844 | F52: 3000
A53: 41035 | C53: СЫВОРОТКА ДЛЯ ЛИЦА ПРОТИВ МОРЩИН NOVAGE+ WRINKLE SMOOTH | D53: 43 | E53: 2827 | F53: 4600
A54: 41044 | C54: ЛЁГКИЙ МУЛЬТИАКТИВНЫЙ ДНЕВНОЙ КРЕМ NOVAGE+ SPF 30 | D54: 25 | E54: 1659 | F54: 2699
A55: 41058 | C55: НАСЫЩЕННЫЙ МУЛЬТИАКТИВНЫЙ НОЧНОЙ КРЕМ NOVAGE+ | D55: 34 | E55: 2213 | F55: 3600
A56: 45590 | C56: КОМПЛЕКСНЫЙ УХОД ПРОТИВ МОРЩИН NOVAGE+ WRINKLE SMOOTH | D56: 115 | E56: 6147 | F56: 9999
C57: предложение со стр. 106
A58: 41029 | C58: ОЧИЩАЮЩИЙ ГЕЛЬ ДЛЯ ЛИЦА NOVAGE+ | D58: 17 | E58: 1137 | F58: 1850
A59: 41033 | C59: КРЕМ ДЛЯ КОЖИ ВОКРУГ ГЛАЗ ПРОТИВ ПИГМЕНТАЦИИ NOVAGE+ BRIGHT INTENSE | D59: 28 | E59: 1844 | F59: 3000
A60: 41040 | C60: СЫВОРОТКА ДЛЯ ЛИЦА ПРОТИВ ПИГМЕНТАЦИИ NOVAGE+ BRIGHT INTENSE | D60: 43 | E60: 2827 | F60: 4600
A61: 41044 | C61: ЛЁГКИЙ МУЛЬТИАКТИВНЫЙ ДНЕВНОЙ КРЕМ NOVAGE+ SPF 30 | D61: 25 | E61: 1659 | F61: 2699
A62: 41058 | C62: НАСЫЩЕННЫЙ МУЛЬТИАКТИВНЫЙ НОЧНОЙ КРЕМ NOVAGE+ | D62: 34 | E62: 2213 | F62: 3600
A63: 45595 | C63: КОМПЛЕКСНЫЙ УХОД ПРОТИВ ПИГМЕНТАЦИИ NOVAGE+ BRIGHT INTENSE | D63: 115 | E63: 6147 | F63: 9999
C64: предложение со стр. 107
A65: 41029 | C65: ОЧИЩАЮЩИЙ ГЕЛЬ ДЛЯ ЛИЦА NOVAGE+ | D65: 17 | E65: 1137 | F65: 1850
A66: 42425 | C66: КРЕМ-ЛИФТИНГ ДЛЯ КОЖИ ВОКРУГ ГЛАЗ NOVAGE+ LIFT + FIRM | D66: 28 | E66: 1844 | F66: 3000
A67: 41037 | C67: СЫВОРОТКА-ЛИФТИНГ ДЛЯ ЛИЦА NOVAGE+ LIFT + FIRM | D67: 43 | E67: 2827 | F67: 4600
A68: 41048 | C68: НАСЫЩЕННЫЙ МУЛЬТИАКТИВНЫЙ ДНЕВНОЙ КРЕМ NOVAGE+ SPF 30 | D68: 25 | E68: 1659 | F68: 2699
A69: 41058 | C69: НАСЫЩЕННЫЙ МУЛЬТИАКТИВНЫЙ НОЧНОЙ КРЕМ NOVAGE+ | D69: 34 | E69: 2213 | F69: 3600
A70: 43691 | C70: КОМПЛЕКСНЫЙ ЛИФТИНГ-УХОД NOVAGE+ LIFT + FIRM (НАСЫЩЕННАЯ ТЕКСТУРА) | D70: 115 | E70: 6147 | F70: 9999
C71: предложение со стр. 107
A72: 41029 | C72: ОЧИЩАЮЩИЙ ГЕЛЬ ДЛЯ ЛИЦА NOVAGE+ | D72: 17 | E72: 1137 | F72: 1850
A73: 41034 | C73: КРЕМ ДЛЯ КОЖИ ВОКРУГ ГЛАЗ ПРОТИВ МОРЩИН NOVAGE+ WRINKLE SMOOTH | D73: 28 | E73: 1844 | F73: 3000
A74: 41039 | C74: АНТИВОЗРАСТНАЯ СЫВОРОТКА ДЛЯ ПРОБЛЕМНОЙ КОЖИ NOVAGE+ BLEMISH + AGE DEFY | D74: 43 | E74: 2827 | F74: 4600
A75: 41044 | C75: ЛЁГКИЙ МУЛЬТИАКТИВНЫЙ ДНЕВНОЙ КРЕМ NOVAGE+ SPF 30 | D75: 25 | E75: 1659 | F75: 2699
A76: 41057 | C76: ЛЁГКИЙ МУЛЬТИАКТИВНЫЙ НОЧНОЙ КРЕМ NOVAGE+ | D76: 34 | E76: 2213 | F76: 3600
A77: 45608 | C77: КОМПЛЕКСНЫЙ АНТИВОЗРАСТНОЙ УХОД ДЛЯ ПРОБЛЕМНОЙ КОЖИ NOVAGE+ BLEMISH + AGE DEFY | D77: 115 | E77: 6147 | F77: 9999
C78: предложение со стр. 108
A79: 38382 | C79: ОЧИЩАЮЩАЯ ПЕНКА-КОМФОРТ ДЛЯ ЛИЦА NOVAGE SKINRELIEF PRO RESILIENT | D79: 17 | E79: 1137 | F79: 1850
A80: 38385 | C80: НОЧНОЙ КРЕМ-КОМФОРТ NOVAGE SKINRELIEF PRO RESILIENT | D80: 30 | E80: 1967 | F80: 3200
A81: 38390 | C81: КРЕМ-КОМФОРТ ДЛЯ КОЖИ ВОКРУГ ГЛАЗ NOVAGE SKINRELIEF PRO RESILIENT | D81: 25 | E81: 1659 | F81: 2700
A82: 38391 | C82: СЫВОРОТКА-КОМФОРТ ДЛЯ ЛИЦА NOVAGE SKINRELIEF PRO RESILIENT | D82: 40 | E82: 2582 | F82: 4200
A83: 40794 | C83: ДНЕВНОЙ КРЕМ-КОМФОРТ NOVAGE SKINRELIEF PRO RESILIENT SPF 30 | D83: 23 | E83: 1475 | F83: 2399
A84: 44480 | C84: КОМПЛЕКСНЫЙ УХОД-КОМФОРТ NOVAGE SKINRELIEF PRO RESILIENT | D84: 104 | E84: 5593 | F84: 9099
C85: предложение со стр. 109
A86: 41029 | C86: ОЧИЩАЮЩИЙ ГЕЛЬ ДЛЯ ЛИЦА NOVAGE+ | D86: 17 | E86: 1137 | F86: 1850
A87: 41070 | C87: ОМОЛАЖИВАЮЩИЙ КРЕМ ДЛЯ КОНТУРА ГЛАЗ И ГУБ NOVAGE+ RESTORE | D87: 30 | E87: 1967 | F87: 3200
A88: 41075 | C88: ОМОЛАЖИВАЮЩАЯ СЫВОРОТКА ДЛЯ ЛИЦА NOVAGE+ RESTORE | D88: 45 | E88: 2951 | F88: 4800
A89: 44098 | C89: ОМОЛАЖИВАЮЩИЙ ДНЕВНОЙ КРЕМ SPF 30 NOVAGE+ RESTORE | D89: 28 | E89: 1843 | F89: 2999
A90: 44285 | C90: ОМОЛАЖИВАЮЩИЙ НОЧНОЙ КРЕМ NOVAGE+ RESTORE | D90: 38 | E90: 2459 | F90: 4000
A91: 45923 | C91: КОМПЛЕКСНЫЙ ОМОЛАЖИВАЮЩИЙ УХОД NOVAGE+ RESTORE | D91: 123 | E91: 6577 | F91: 10699
C92: предложение со стр. 113-115
A93: 29699 | B93: + | C93: КОМПЛЕКС «МУЛЬТИВИТАМИНЫ И МИНЕРАЛЫ» ДЛЯ ДЕТЕЙ | D93: 24 | E93: 1537 | F93: 2500
C94: ЦЕНА 1499 РУБ. ПРИ ЗАКАЗЕ НА 3000 РУБ. ИЗ ЭТОГО КАТАЛОГА ИЛИ НА САЙТЕ В ПЕРИОД ДЕЙСТВИЯ КАТАЛОГА (КРОМЕ ПРОДУКТОВ-УЧАСТНИКОВ АКЦИИ 46045, 47513, 29699, 38836, 38838, 40745, 45306, 45307, 37285, 37289, 37290) | D94: 14 | E94: 922 | F94: 1499
A95: 38836 | B95: + | C95: WELLOSOPHY WELLNESS PACK ДЛЯ МУЖЧИН | D95: 51 | E95: 3258 | F95: 5300
A96: 38838 | B96: + | C96: WELLOSOPHY WELLNESS PACK ДЛЯ ЖЕНЩИН | D96: 51 | E96: 3258 | F96: 5300
C97: ЦЕНА 3199 РУБ. ПРИ ЗАКАЗЕ НА 3000 РУБ. ИЗ ЭТОГО КАТАЛОГА ИЛИ НА САЙТЕ В ПЕРИОД ДЕЙСТВИЯ КАТАЛОГА (КРОМЕ ПРОДУКТОВ-УЧАСТНИКОВ АКЦИИ 46045, 47513, 29699, 38836, 38838, 40745, 45306, 45307, 37285, 37289, 37290) | D97: 31 | E97: 1967 | F97: 3199
A98: 40745 | B98: + | C98: ПИТАТЕЛЬНЫЙ СУП ДЛЯ КОНТРОЛЯ ВЕСА - ГРИБНОЙ ВКУС | D98: 70 | E98: 4242 | F98: 6900
A99: 45306 | B99: + | C99: ПИТАТЕЛЬНЫЙ КОКТЕЙЛЬ ДЛЯ КОНТРОЛЯ ВЕСА - ВАНИЛЬНЫЙ ВКУС | D99: 70 | E99: 4242 | F99: 6900
A100: 45307 | B100: + | C100: ПИТАТЕЛЬНЫЙ КОКТЕЙЛЬ ДЛЯ КОНТРОЛЯ ВЕСА - ШОКОЛАДНЫЙ ВКУС | D100: 70 | E100: 4242 | F100: 6900
C101: ЦЕНА 4149 РУБ. ПРИ ЗАКАЗЕ НА 3000 РУБ. ИЗ ЭТОГО КАТАЛОГА ИЛИ НА САЙТЕ В ПЕРИОД ДЕЙСТВИЯ КАТАЛОГА (КРОМЕ ПРОДУКТОВ-УЧАСТНИКОВ АКЦИИ 46045, 47513, 29699, 38836, 38838, 40745, 45306, 45307, 37285, 37289, 37290) | D101: 42 | E101: 2550 | F101: 4149
A102: 37285 | B102: + | C102: СУХАЯ СМЕСЬ ДЛЯ КОКТЕЙЛЯ NATURAL BALANCE - КЛУБНИЧНЫЙ ВКУС | D102: 54 | E102: 3442 | F102: 5600
A103: 37289 | B103: + | C103: СУХАЯ СМЕСЬ ДЛЯ КОКТЕЙЛЯ NATURAL BALANCE - ШОКОЛАДНЫЙ ВКУС | D103: 54 | E103: 3442 | F103: 5600
A104: 37290 | B104: + | C104: СУХАЯ СМЕСЬ ДЛЯ КОКТЕЙЛЯ NATURAL BALANCE - ВАНИЛЬНЫЙ ВКУС | D104: 54 | E104: 3442 | F104: 5600
C105: ЦЕНА 3349 РУБ. ПРИ ЗАКАЗЕ НА 3000 РУБ. ИЗ ЭТОГО КАТАЛОГА ИЛИ НА САЙТЕ В ПЕРИОД ДЕЙСТВИЯ КАТАЛОГА (КРОМЕ ПРОДУКТОВ-УЧАСТНИКОВ АКЦИИ 46045, 47513, 29699, 38836, 38838, 40745, 45306, 45307, 37285, 37289, 37290) | D105: 32 | E105: 2059 | F105: 3349
C106: предложение со стр. 143-163
A107: 46970 | B107: + | C107: =VLOOKUP(A107,'05 КАТАЛОГ`26 (1)'!$1:$1048576,5,0) -> КРЕМ ДЛЯ ДУША MILK & HONEY GOLD | D107: 5 | E107: 307 | F107: 499
...
