Workbook
Name Color_GM: #REF!
Name Target_GM: #REF!
Name МЯГКИЙ_ДВУХСТОРОННИЙ_КАРАНДАШ_ДЛЯ_ГЛАЗ___СЛИВОЧНАЯ_КАРАМЕЛЬ__СТР._83_КАТАЛОГА: '[1]10 КАТАЛОГ`08 (1)'!#REF!
Name МЯГКИЙ_ДВУХСТОРОННИЙ_КАРАНДАШ_ДЛЯ_ГЛАЗ___СЛИВОЧНАЯ_КАРАМЕЛЬ__СТР._83_КАТАЛОГА: '[1]10 КАТАЛОГ`08 (1)'!#REF!
Name МЯГКИЙ_ДВУХСТОРОННИЙ_КАРАНДАШ_ДЛЯ_ГЛАЗ___СЛИВОЧНАЯ_КАРАМЕЛЬ__СТР._83_КАТАЛОГА: '10 КАТАЛОГ`24 (1)'!#REF!

Sheet 10 КАТАЛОГ`24 (1)
E1: НОВИНКИ КАТАЛОГА
A2: КОД | B2: СКИДКА | C2: СТР. | D2: АКЦИЯ | E2: НАИМЕНОВАНИЕ | F2: ББ | G2: ОП | H2: ПЦ
A3: 44316 | C3: 136 | E3: ПАРФЮМЕРНАЯ ВОДА INFINITA MY SUNSHINE (ПРОБНИК) | F3: - | G3: - | H3: 35
A4: 46043 | B4: 0.33377778 | C4: 165 | E4: ТУАЛЕТНАЯ ВОДА WOMEN'S COLLECTION CHARMING VIOLET | F4: 15 | G4: 962 | H4: 1499
A5: 46044 | B5: 0.33377778 | C5: 163 | E5: ТУАЛЕТНАЯ ВОДА MEN'S COLLECTION AGAVE POWER | F5: 15 | G5: 962 | H5: 1499
A6: 46366 | B6: 0.46307692 | C6: 113 | E6: ОСВЕЖАЮЩИЙ ГЕЛЬ ДЛЯ ИНТИМНОЙ ГИГИЕНЫ FEMINELLE. ЛИМИТИРОВАННЫЙ ВЫПУСК | F6: 3 | G6: 224 | H6: 349
A7: 47517 | B7: 0.46216216 | C7: 82 | E7: ЩЁТОЧКА ДЛЯ ОЧИЩЕНИЯ ЛИЦА | F7: 2 | G7: 64 | H7: 199
A8: 47520 | B8: 0.44193548 | C8: 55 | E8: МАТИРУЮЩИЙ РОЛИК | F8: 5 | G8: 167 | H8: 519
A9: 47522 | B9: 0.44193548 | C9: 83 | E9: СПОНЖ КОННЯКУ С УГЛЁМ | F9: 5 | G9: 167 | H9: 519
E11: НОВИНКИ WELLOSOPHY
A12: КОД | B12: СКИДКА | C12: СТР. | D12: АКЦИЯ | E12: НАИМЕНОВАНИЕ | F12: ББ | G12: ОП | H12: ПЦ
A13: 47417 | C13: 106 | E13: ШЕЙКЕР | F13: 10 | G13: 321 | H13: 999
E14: WELLOSOPHY
A15: КОД | B15: СКИДКА | C15: СТР. | D15: АКЦИЯ | E15: НАИМЕНОВАНИЕ | F15: ББ | G15: ОП | H15: ПЦ
A16: 22467 | C16: 109 | E16: «ОМЕГА-3» ДЛЯ ДЕТЕЙ | F16: 24 | G16: 1475 | H16: 2300
A17: 27996 | C17: 109 | E17: КОМПЛЕКС «МУЛЬТИВИТАМИНЫ И МИНЕРАЛЫ» ДЛЯ ДЕТЕЙ | F17: 17 | G17: 1090 | H17: 1700
A18: 29695 | C18: 107 | E18: СУП «НЭЧУРАЛ БАЛАНС» - СПАРЖА | F18: 52 | G18: 3208 | H18: 5000
A19: 29706 | C19: 107 | E19: НУТРИКОМПЛЕКС ДЛЯ ВОЛОС И НОГТЕЙ | F19: 29 | G19: 1797 | H19: 2800
A20: 31750 | B20: 0.21782609 | C20: 107 | E20: ПРЕБИОТИЧЕСКИЙ НАПИТОК С ПИЩЕВЫМИ ВОЛОКНАМИ | F20: 19 | G20: 1154 | H20: 1799
A21: 37285 | C21: 105 | E21: СУХАЯ СМЕСЬ ДЛЯ КОКТЕЙЛЯ «НЭЧУРАЛ БАЛАНС» - КЛУБНИЧНЫЙ ВКУС | F21: 52 | G21: 3208 | H21: 5000
A22: 37289 | C22: 105 | E22: СУХАЯ СМЕСЬ ДЛЯ КОКТЕЙЛЯ «НЭЧУРАЛ БАЛАНС» - ШОКОЛАДНЫЙ ВКУС | F22: 52 | G22: 3208 | H22: 5000
A23: 37290 | C23: 105 | E23: СУХАЯ СМЕСЬ ДЛЯ КОКТЕЙЛЯ «НЭЧУРАЛ БАЛАНС» - ВАНИЛЬНЫЙ ВКУС | F23: 52 | G23: 3208 | H23: 5000
A24: 37293 | C24: 105 | E24: ПРОТЕИНОВЫЙ КОМПЛЕКС | F24: 52 | G24: 3208 | H24: 5000
A25: 38556 | C25: 107 | E25: КОМПЛЕКС «ОМЕГА-3» | F25: 24 | G25: 1475 | H25: 2300
A26: 38557 | B26: 0.14321429 | C26: 99 | E26: КОМПЛЕКС «АСТАКСАНТИН И ЭКСТРАКТ ЧЕРНИКИ» | F26: 25 | G26: 1539 | H26: 2399
A27: 38558 | C27: 107 | E27: КОМПЛЕКС «МУЛЬТИВИТАМИНЫ И МИНЕРАЛЫ» ДЛЯ МУЖЧИН | F27: 29 | G27: 1797 | H27: 2800
A28: 38559 | C28: 107 | E28: КОМПЛЕКС «МУЛЬТИВИТАМИНЫ И МИНЕРАЛЫ» ДЛЯ ЖЕНЩИН | F28: 29 | G28: 1797 | H28: 2800
A29: 38836 | C29: 101 | E29: WELLOSOPHY WELLNESS PACK ДЛЯ МУЖЧИН | F29: 50 | G29: 2887 | H29: 4500
A30: 38838 | C30: 101 | E30: WELLOSOPHY WELLNESS PACK ДЛЯ ЖЕНЩИН | F30: 50 | G30: 2887 | H30: 4500
A31: 40745 | C31: 103 | E31: ПИТАТЕЛЬНЫЙ СУП ДЛЯ КОНТРОЛЯ ВЕСА - ГРИБНОЙ ВКУС | F31: 70 | G31: 3850 | H31: 6000
A32: 45306 | C32: 102 | E32: ПИТАТЕЛЬНЫЙ КОКТЕЙЛЬ ДЛЯ КОНТРОЛЯ ВЕСА - ВАНИЛЬНЫЙ ВКУС | F32: 70 | G32: 3850 | H32: 6000
A33: 45307 | C33: 102 | E33: ПИТАТЕЛЬНЫЙ КОКТЕЙЛЬ ДЛЯ КОНТРОЛЯ ВЕСА - ШОКОЛАДНЫЙ ВКУС | F33: 70 | G33: 3850 | H33: 6000
A34: 45309 | C34: 107 | E34: КОМПЛЕКС «МОРСКОЙ КАЛЬЦИЙ И ВИТАМИН D» | F34: 24 | G34: 1475 | H34: 2300
A35: 46068 | C35: 107 | E35: МЕРНАЯ ЛОЖКА | F35: 1 | G35: 38 | H35: 119
A36: 46664 | C36: 107 | E36: ШЕЙКЕР | F36: 14 | G36: 449 | H36: 1399
A37: 46685 | C37: 104 | E37: ОХЛАЖДАЮЩЕЕ ПОЛОТЕНЦЕ | F37: 7 | G37: 224 | H37: 699
E39: КАТАЛОГ
A40: КОД | B40: СКИДКА | C40: СТР. | D40: АКЦИЯ | E40: НАИМЕНОВАНИЕ | F40: ББ | G40: ОП | H40: ПЦ
A41: 12760 | B41: 0.55526316 | C41: 13 | E41: СПЕЦИАЛЬНОЕ СМЯГЧАЮЩЕЕ СРЕДСТВО | F41: 2 | G41: 109 | H41: 169
A42: 13659 | B42: 0.34653846 | C42: 77 | E42: КЛЕТОЧНЫЙ КРЕМ МОЛОДОСТИ DIAMOND CELLULAR | F42: 17 | G42: 1090 | H42: 1699
A43: 18437 | B43: 0.34653846 | C43: 77 | E43: НОЧНОЙ ВОССТАНАВЛИВАЮЩИЙ КЛЕТОЧНЫЙ КРЕМ DIAMOND CELLULAR | F43: 17 | G43: 1090 | H43: 1699
A44: 20574 | B44: 0.502 | C44: 73 | E44: ПОВЯЗКА НА ГОЛОВУ | F44: 2 | G44: 80 | H44: 249
A45: 21339 | C45: 77 | E45: МИЦЕЛЛЯРНЫЙ ОЧИЩАЮЩИЙ ЛОСЬОН DIAMOND CELLULAR | F45: 15 | G45: 994 | H45: 1550
A46: 22815 | B46: 0.54842105 | C46: 25 | E46: ПОДТЯГИВАЮЩИЙ КРЕМ ДЛЯ ВЕК ROYAL VELVET | F46: 4 | G46: 275 | H46: 429
A47: 23378 | B47: 0.24692308 | C47: 21 | E47: СОЛНЦЕЗАЩИТНЫЙ КРЕМ ДЛЯ ЛИЦА SUN ZONE SPF 50 | F47: 10 | G47: 628 | H47: 979
A48: 24547 | B48: 0.38741935 | C48: 25 | E48: ИНТЕНСИВНО ПОДТЯГИВАЮЩИЕ КАПСУЛЫ ДЛЯ ЛИЦА ROYAL VELVET | F48: 19 | G48: 1218 | H48: 1899
A49: 26825 | B49: 0.46216216 | C49: 80 | E49: ИНСТРУМЕНТ ДЛЯ ОЧИСТКИ ЛИЦА | F49: 2 | G49: 64 | H49: 199
A50: 29038 | B50: 0.45368421 | C50: 83 | E50: СПОНЖ КОННЯКУ | F50: 5 | G50: 167 | H50: 519
A51: 29043 | B51: 0.40071429 | C51: 54 | E51: ЗЕРКАЛО | F51: 8 | G51: 269 | H51: 839
A52: 29446 | B52: 0.30401961 | C52: 147 | E52: КОМПЛЕКСНЫЙ УХОД ДЛЯ МУЖСКОЙ КОЖИ NOVAGE MEN | F52: 85 | G52: 4555 | H52: 7099
A53: 30058 | B53: 0.372 | C53: 160 | E53: ТУАЛЕТНАЯ ВОДА MEN'S COLLECTION CITRUS TONIC | F53: 11 | G53: 705 | H53: 1099
A54: 30568 | B54: 0.23857143 | C54: 21 | E54: ДЕТСКИЙ СОЛНЦЕЗАЩИТНЫЙ ЛОСЬОН SUN ZONE SPF 50 | F54: 16 | G54: 1026 | H54: 1599
A55: 31606 | B55: 0.35645161 | C55: 128 | E55: УВЛАЖНЯЮЩИЙ КРЕМ ДЛЯ РУК «МОЛОКО И МЕД - ЗОЛОТАЯ СЕРИЯ» | F55: 4 | G55: 256 | H55: 399
A56: 31774 | B56: 0.30076923 | C56: 96 | E56: КОМПЛЕКСНЫЙ ОМОЛАЖИВАЮЩИЙ УХОД NOVAGE TIME RESTORE | F56: 120 | G56: 6416 | H56: 9999
A57: 31825 | B57: 0.34883721 | C57: 146 | E57: МУЖСКАЯ ТУАЛЕТНАЯ ВОДА POSSESS | F57: 28 | G57: 1797 | H57: 2800
... A59: 31851 | B59: 0.400625 | C59: 116 | E59: ЛОСЬОН ДЛЯ РУК И ТЕЛА С ЛИМОНОМ И ВЕРБЕНОЙ ESSENSE & CO. | F59: 10 | G59: 615 | H59: 959
A60: 32139 | C60: 38 | E60: СРЕДСТВО ДЛЯ СНЯТИЯ МАКИЯЖА THE ONE | F60: 9 | G60: 577 | H60: 900
A61: 32627 | B61: 0.2583871 | C61: 96 | E61: ОМОЛАЖИВАЮЩИЙ ДНЕВНОЙ КРЕМ SPF 15 NOVAGE TIME RESTORE | F61: 23 | G61: 1475 | H61: 2299
A62: 32628 | C62: 96 | E62: ОМОЛАЖИВАЮЩИЙ НОЧНОЙ КРЕМ NOVAGE TIME RESTORE | F62: 31 | G62: 1989 | H62: 3100
A63: 32629 | C63: 96 | E63: ОМОЛАЖИВАЮЩИЙ КРЕМ ДЛЯ КОНТУРА ГЛАЗ И ГУБ NOVAGE TIME RESTORE | F63: 25 | G63: 1604 | H63: 2500
A64: 32630 | C64: 96 | E64: ОМОЛАЖИВАЮЩАЯ СЫВОРОТКА ДЛЯ ЛИЦА И ШЕИ NOVAGE TIME RESTORE | F64: 40 | G64: 2567 | H64: 4000
A65: 32919 | B65: 0.20976744 | C65: 51 | E65: ШЕЛКОВАЯ ТОНАЛЬНАЯ ОСНОВА-ФЛЮИД GIORDANI GOLD - ВАНИЛЬНЫЙ | F65: 17 | G65: 1090 | H65: 1699
A66: 32920 | B66: 0.20976744 | C66: 51 | E66: - ФАРФОРОВЫЙ | F66: 17 | G66: 1090 | H66: 1699
A67: 32921 | B67: 0.20976744 | C67: 51 | E67: - СЛОНОВАЯ КОСТЬ | F67: 17 | G67: 1090 | H67: 1699
A68: 32922 | B68: 0.20976744 | C68: 51 | E68: - ПЕСОЧНЫЙ БЕЖ | F68: 17 | G68: 1090 | H68: 1699
A69: 32923 | B69: 0.20976744 | C69: 51 | E69: - ЕСТЕСТВЕННЫЙ БЕЖ | F69: 17 | G69: 1090 | H69: 1699
A70: 33142 | B70: 0.562 | C70: 166 | E70: ДЕЗОДОРАНТ-АНТИПЕРСПИРАНТ ДЛЯ ЭКСТРЕМАЛЬНОЙ ЗАЩИТЫ ACTIVELLE | F70: 2 | G70: 141 | H70: 219
A71: 33144 | B71: 0.52539683 | C71: 166 | E71: СПРЕЙ ДЕЗОДОРАНТ С УХАЖИВАЮЩИМ КОМПЛЕКСОМ ACTIVELLE | F71: 3 | G71: 192 | H71: 299
A72: 33198 | C72: 147 | E72: СРЕДСТВО ДЛЯ УМЫВАНИЯ И СКРАБ 2-В-1 NOVAGE MEN | F72: 15 | G72: 962 | H72: 1500
A73: 33199 | C73: 147 | E73: ТОНИЗИРУЮЩИЙ ГЕЛЬ ДЛЯ КОЖИ ВОКРУГ ГЛАЗ NOVAGE MEN | F73: 23 | G73: 1475 | H73: 2300
A74: 33200 | C74: 147 | E74: УВЛАЖНЯЮЩАЯ ЭНЕРГОСЫВОРОТКА ДЛЯ ЛИЦА NOVAGE MEN | F74: 37 | G74: 2374 | H74: 3700
A75: 33201 | B75: 0.25962963 | C75: 147 | E75: УВЛАЖНЯЮЩИЙ ГЕЛЬ-КРЕМ ПРОТИВ СТАРЕНИЯ КОЖИ NOVAGE MEN | F75: 20 | G75: 1283 | H75: 1999
A76: 33447 | B76: 0.35645161 | C76: 128 | E76: СКРАБ ДЛЯ РУК «МОЛОКО И МЕД - ЗОЛОТАЯ СЕРИЯ» | F76: 4 | G76: 256 | H76: 399
A77: 33654 | C77: 5 | E77: ТУАЛЕТНАЯ ВОДА MISTER GIORDANI | F77: 33 | G77: 2117 | H77: 3300
A78: 33963 | B78: 0.556 | C78: 74 | E78: ТУАЛЕТНАЯ ВОДА ON THE EDGE | F78: 10 | G78: 641 | H78: 999
A79: 33984 | C79: 96 | E79: ОЧИЩАЮЩИЙ ГЕЛЬ-ТОНИК ДЛЯ УМЫВАНИЯ NOVAGE | F79: 16 | G79: 1027 | H79: 1600
A80: 33988 | C80: 94 | E80: ОБНОВЛЯЮЩИЙ ПИЛИНГ ДЛЯ ЛИЦА NOVAGE | F80: 16 | G80: 1059 | H80: 1650
A81: 34076 | B81: 0.49365079 | C81: 150 | E81: ШАРИКОВЫЙ ДЕЗОДОРАНТ-АНТИПЕРСПИРАНТ BE THE LEGEND | F81: 3 | G81: 205 | H81: 319
A82: 34079 | B82: 0.49365079 | C82: 151 | E82: ШАРИКОВЫЙ ДЕЗОДОРАНТ MISS GIORDANI | F82: 3 | G82: 205 | H82: 319
A83: 34498 | B83: 0.46307692 | C83: 112 | E83: ЗАЩИТНЫЙ ГЕЛЬ ДЛЯ ИНТИМНОЙ ГИГИЕНЫ FEMINELLE | F83: 3 | G83: 224 | H83: 349
A84: 34647 | B84: 0.49741935 | C84: 54 | E84: КОМПАКТНАЯ МАТИРУЮЩАЯ ПУДРА THE ONE EVERLASTING - СВЕТЛЫЙ | F84: 8 | G84: 500 | H84: 779
A85: 34648 | B85: 0.49741935 | C85: 54 | E85: - СРЕДНИЙ | F85: 8 | G85: 500 | H85: 779
A86: 34649 | B86: 0.49741935 | C86: 54 | E86: - ТЁМНЫЙ | F86: 8 | G86: 500 | H86: 779
A87: 34650 | B87: 0.49741935 | C87: 54 | E87: - ИНТЕНСИВНЫЙ ТЁМНЫЙ | F87: 8 | G87: 500 | H87: 779
A88: 34819 | B88: 0.50166667 | C88: 38 | D88: + | E88: ОЧИЩАЮЩИЙ КРЕМ ДЛЯ УМЫВАНИЯ LOVE NATURE | F88: 3 | G88: 192 | H88: 299
A89: 34841 | B89: 0.40166667 | C89: 85 | E89: ОЧИЩАЮЩИЙ ГЕЛЬ ДЛЯ УМЫВАНИЯ С ОРГАНИЧЕСКИМ ЧАЙНЫМ ДЕРЕВОМ И ЛАЙМОМ LOVE NATURE | F89: 4 | G89: 230 | H89: 359
A90: 34843 | B90: 0.40166667 | C90: 85 | E90: СУЖАЮЩИЙ ПОРЫ ТОНИК ДЛЯ ЛИЦА С ОРГАНИЧЕСКИМ ЧАЙНЫМ ДЕРЕВОМ И ЛАЙМОМ LOVE NATURE | F90: 4 | G90: 230 | H90: 359
A91: 34849 | B91: 0.43230769 | C91: 85 | E91: АНТИБАКТЕРИАЛЬНОЕ СРЕДСТВО ДЛЯ ЛИЦА LOVE NATURE | F91: 4 | G91: 237 | H91: 369
A92: 34855 | B92: 0.43230769 | C92: 85 | E92: АНТИБАКТЕРИАЛЬНЫЙ КАРАНДАШ-КОРРЕКТОР "ЧАЙНОЕ ДЕРЕВО" | F92: 4 | G92: 237 | H92: 369
A93: 34891 | B93: 0.23857143 | C93: 21 | E93: СОЛНЦЕЗАЩИТНЫЙ СПРЕЙ ДЛЯ ЛИЦА И ТЕЛА ORIFLAME SUN 360 С SPF 50 | F93: 16 | G93: 1026 | H93: 1599
A94: 34920 | B94: 0.50142857 | C94: 148 | E94: НЕВИДИМЫЙ ГЕЛЬ ДЛЯ УКЛАДКИ ВОЛОС NORTH FOR MEN | F94: 3 | G94: 224 | H94: 349
A95: 35073 | B95: 0.2968 | C95: 94 | E95: ИНТЕНСИВНЫЙ АНТИВОЗРАСТНОЙ КРЕМ ДЛЯ РУК С SPF 25 NOVAGE | F95: 9 | G95: 564 | H95: 879
A96: 35076 | B96: 0.28607143 | C96: 94 | E96: КОНЦЕНТРИРОВАННЫЙ КРЕМ-СКУЛЬПТОР ДЛЯ ШЕИ И ДЕКОЛЬТЕ NOVAGE | F96: 20 | G96: 1283 | H96: 1999
A97: 35424 | B97: 0.49322034 | C97: 66 | E97: ЖИДКАЯ ПОДВОДКА ONCOLOUR - ЧЕРНЫЙ | F97: 3 | G97: 192 | H97: 299
A98: 35639 | B98: 0.50151515 | C98: 69 | E98: BB-КРЕМ C SPF 10 ONCOLOUR - СВЕТЛЫЙ | F98: 3 | G98: 211 | H98: 329
A99: 35640 | B99: 0.50151515 | C99: 69 | E99: - ЕСТЕСТВЕННЫЙ | F99: 3 | G99: 211 | H99: 329
A100: 35641 | B100: 0.50151515 | C100: 69 | E100: - СРЕДНИЙ | F100: 3 | G100: 211 | H100: 329
... A115: 35892 | B115: 0.29466667 | C115: 117 | E115: ОЧИЩАЮЩЕЕ СРЕДСТВО ДЛЯ ДУША BEAUTANICALS | F115: 5 | G115: 340 | H115: 529
A116: 35910 | B116: 0.50166667 | C116: 38 | D116: + | E116: ОЧИЩАЮЩЕЕ СРЕДСТВО ДЛЯ СИЯНИЯ ЛИЦА С ОРГАНИЧЕСКИМ АБРИКОСОМ И АПЕЛЬСИНОМ LOVE NATURE | F116: 3 | G116: 192 | H116: 299
A117: 35957 | B117: 0.351 | C117: 129 | E117: ШАМПУНЬ MILK & HONEY GOLD | F117: 6 | G117: 417 | H117: 649
...

Sheet 10 КАТАЛОГ`24 (2)
A1: ПРОБНИК | B1: ПРОДУКТ | C1: ТЕСТЕРЫ | D1: ЦЕНА
A2: 11037 | B2: 42490 | C2: ТУАЛЕТНАЯ ВОДА ASCENDANT | D2: =VLOOKUP(A2,[2]Report!$1:$1048576,9,0) -> #N/A
A3: 11365 | B3: =VLOOKUP(A3,'[3]02 КАТАЛОГ`24 (2)'!$1:$1048576,2,0) -> 42495 | C3: =VLOOKUP(A3,'[3]02 КАТАЛОГ`24 (2)'!$1:$1048576,3,0) -> ПАРФЮМЕРНАЯ ВОДА AMBER ELIXIR | D3: =VLOOKUP(A3,[2]Report!$1:$1048576,9,0) -> #N/A
A4: 22443 | B4: 42751 | C4: ТУАЛЕТНАЯ ВОДА LOVE POTION | D4: =VLOOKUP(A4,[2]Report!$1:$1048576,9,0) -> #N/A
A5: 30044 | B5: 42514 | C5: ПАРФЮМЕРНАЯ ВОДА VOLARE | D5: =VLOOKUP(A5,[2]Report!$1:$1048576,9,0) -> #N/A
A6: 30129 | B6: 42507 | C6: ТУАЛЕТНАЯ ВОДА ECLAT FEMME | D6: =VLOOKUP(A6,[2]Report!$1:$1048576,9,0) -> #N/A
A7: 30321 | B7: 42864 | C7: ТУАЛЕТНАЯ ВОДА ECLAT HOMME | D7: =VLOOKUP(A7,[2]Report!$1:$1048576,9,0) -> #N/A
A8: 30400 | B8: 30399 | C8: ПАРФЮМЕРНАЯ ВОДА MISS GIORDANI | D8: =VLOOKUP(A8,[2]Report!$1:$1048576,9,0) -> #N/A
A9: 30557 | B9: 30468 | C9: ТУАЛЕТНАЯ ВОДА BE THE LEGEND | D9: =VLOOKUP(A9,[2]Report!$1:$1048576,9,0) -> #N/A
A10: 30885 | B10: 42519 | C10: ПАРФЮМЕРНАЯ ВОДА POSSESS | D10: =VLOOKUP(A10,[2]Report!$1:$1048576,9,0) -> #N/A
A11: 31002 | B11: 30058 | C11: ТУАЛЕТНАЯ ВОДА MEN´S COLLECTION CITRUS TONIC | D11: =VLOOKUP(A11,[2]Report!$1:$1048576,9,0) -> #N/A
A12: 31003 | B12: 42518 | C12: ТУАЛЕТНАЯ ВОДА MEN´S COLLECTION DARK WOOD | D12: =VLOOKUP(A12,[2]Report!$1:$1048576,9,0) -> #N/A
A13: 31292 | B13: =VLOOKUP(A13,'[3]02 КАТАЛОГ`24 (2)'!$1:$1048576,2,0) -> 42499 | C13: =VLOOKUP(A13,'[3]02 КАТАЛОГ`24 (2)'!$1:$1048576,3,0) -> ТУАЛЕТНАЯ ВОДА ECLAT FEMME WEEKEND | D13: =VLOOKUP(A13,[2]Report!$1:$1048576,9,0) -> #N/A
A14: 31494 | B14: 42815 | C14: ПАРФЮМЕРНАЯ ВОДА LOVE POTION SECRETS | D14: =VLOOKUP(A14,[2]Report!$1:$1048576,9,0) -> #N/A
A15: 31817 | B15: 42503 | C15: ПАРФЮМЕРНАЯ ВОДА GIORDANI GOLD ESSENZA | D15: =VLOOKUP(A15,[2]Report!$1:$1048576,9,0) -> #N/A
A16: 31824 | B16: 31825 | C16: МУЖСКАЯ ТУАЛЕТНАЯ ВОДА POSSESS | D16: =VLOOKUP(A16,[2]Report!$1:$1048576,9,0) -> #N/A
A17: 32234 | B17: 42502 | C17: ТУАЛЕТНАЯ ВОДА ELVIE | D17: =VLOOKUP(A17,[2]Report!$1:$1048576,9,0) -> #N/A
A18: 32441 | B18: 32438 | C18: ТУАЛЕТНАЯ ВОДА WOMEN'S COLLECTION INNOCENT WHITE LILAC | D18: =VLOOKUP(A18,[2]Report!$1:$1048576,9,0) -> #N/A
A19: 32442 | B19: 42828 | C19: ТУАЛЕТНАЯ ВОДА WOMEN'S COLLECTION DELICATE CHERRY BLOSSOM | D19: =VLOOKUP(A19,[2]Report!$1:$1048576,9,0) -> #N/A
A20: 33045 | B20: 42865 | C20: ПАРФЮМЕРНАЯ ВОДА AMBER ELIXIR CRYSTAL | D20: =VLOOKUP(A20,[2]Report!$1:$1048576,9,0) -> #N/A
A21: 33649 | B21: 33650 | C21: ПАРФЮМЕРНАЯ ВОДА POSSESS THE SECRET MAN | D21: =VLOOKUP(A21,[2]Report!$1:$1048576,9,0) -> #N/A
A22: 33653 | B22: 33654 | C22: ТУАЛЕТНАЯ ВОДА MISTER GIORDANI | D22: =VLOOKUP(A22,[2]Report!$1:$1048576,9,0) -> #N/A
A23: 34145 | B23: 42520 | C23: ТУАЛЕТНАЯ ВОДА LUCIA BRIGHT AURA | D23: =VLOOKUP(A23,[2]Report!$1:$1048576,9,0) -> #N/A
A24: 34506 | B24: 42741 | C24: ТУАЛЕТНАЯ ВОДА MAGNETISTA EDP VIAL | D24: =VLOOKUP(A24,[2]Report!$1:$1048576,9,0) -> #N/A
A25: 34612 | B25: 33201 | C25: УВЛАЖНЯЮЩИЙ ГЕЛЬ-КРЕМ ПРОТИВ СТАРЕНИЯ КОЖИ NOVAGE MEN | D25: =VLOOKUP(A25,[2]Report!$1:$1048576,9,0) -> #N/A
A26: 34613 | B26: 33200 | C26: УВЛАЖНЯЮЩАЯ ЭНЕРГОСЫВОРОТКА ДЛЯ ЛИЦА NOVAGE MEN | D26: =VLOOKUP(A26,[2]Report!$1:$1048576,9,0) -> #N/A
A27: 35084 | B27: 33984 | C27: ОЧИЩАЮЩИЙ ГЕЛЬ-ТОНИК ДЛЯ УМЫВАНИЯ NOVAGE | D27: =VLOOKUP(A27,[2]Report!$1:$1048576,9,0) -> #N/A
A28: 35198 | B28: 32630 | C28: ОМОЛАЖИВАЮЩАЯ СЫВОРОТКА ДЛЯ ЛИЦА И ШЕИ NOVAGE TIME RESTORE | D28: =VLOOKUP(A28,[2]Report!$1:$1048576,9,0) -> #N/A
... A40: 35658 | B40: 42508 | C40: ТУАЛЕТНАЯ ВОДА JOYCE TURQUOISE | D40: =VLOOKUP(A40,[2]Report!$1:$1048576,9,0) -> #N/A
A41: 35662 | B41: 35661 | C41: ПАРФЮМЕРНАЯ ВОДА VOLARE MOMENTS | D41: =VLOOKUP(A41,[2]Report!$1:$1048576,9,0) -> #N/A
A42: 35664 | B42: 42837 | C42: ТУАЛЕТНАЯ ВОДА MISTER GIORDANI AQUA | D42: =VLOOKUP(A42,[2]Report!$1:$1048576,9,0) -> #N/A
A43: 35666 | B43: 35665 | C43: ТУАЛЕТНАЯ ВОДА GLACIER | D43: =VLOOKUP(A43,[2]Report!$1:$1048576,9,0) -> #N/A
A44: 35668 | B44: 42816 | C44: ТУАЛЕТНАЯ ВОДА GLACIER ROCK | D44: =VLOOKUP(A44,[2]Report!$1:$1048576,9,0) -> #N/A
A45: 35670 | B45: 42739 | C45: ТУАЛЕТНАЯ ВОДА GLACIER FIRE | D45: =VLOOKUP(A45,[2]Report!$1:$1048576,9,0) -> #N/A
A46: 35674 | B46: 42726 | C46: ТУАЛЕТНАЯ ВОДА DEBONAIR | D46: =VLOOKUP(A46,[2]Report!$1:$1048576,9,0) -> #N/A
A47: 35676 | B47: 37772 | C47: ТУАЛЕТНАЯ ВОДА JOYCE JADE | D47: =VLOOKUP(A47,[2]Report!$1:$1048576,9,0) -> #N/A
A48: 38525 | B48: 38527 | C48: ПАРФЮМЕРНАЯ ВОДА ASCENDANT INTENSE | D48: =VLOOKUP(A48,[2]Report!$1:$1048576,9,0) -> #N/A
A49: 38546 | B49: 38550 | C49: МУЖСКАЯ ПАРФЮМЕРНАЯ ВОДА NORDIC WATERS | D49: =VLOOKUP(A49,[2]Report!$1:$1048576,9,0) -> #N/A
A50: 38548 | B50: 43122 | C50: ЖЕНСКАЯ ПАРФЮМЕРНАЯ ВОДА NORDIC WATERS | D50: =VLOOKUP(A50,[2]Report!$1:$1048576,9,0) -> #N/A
A51: 38569 | B51: 38571 | C51: ТУАЛЕТНАЯ ВОДА .SE BLAZING WARMTH | D51: =VLOOKUP(A51,[2]Report!$1:$1048576,9,0) -> #N/A
A52: 38579 | B52: =VLOOKUP(A52,'[3]02 КАТАЛОГ`24 (2)'!$1:$1048576,2,0) -> 38587 | C52: =VLOOKUP(A52,'[3]02 КАТАЛОГ`24 (2)'!$1:$1048576,3,0) -> ПАРФЮМЕРНАЯ ВОДА SIGNATURE FOR HIM | D52: =VLOOKUP(A52,[2]Report!$1:$1048576,9,0) -> #N/A
A53: 38598 | B53: 38540 | C53: ПАРФЮМЕРНАЯ ВОДА SIGNATURE FOR HER | D53: =VLOOKUP(A53,[2]Report!$1:$1048576,9,0) -> #N/A
A54: 41163 | B54: 35679 | C54: ДУХИ ALL OR NOTHING | D54: =VLOOKUP(A54,[2]Report!$1:$1048576,9,0) -> #N/A
A55: 41183 | B55: 38391 | C55: СЫВОРОТКА-КОМФОРТ ДЛЯ ЛИЦА NOVAGE SKINRELIEF PRO RESILIENT | D55: =VLOOKUP(A55,[2]Report!$1:$1048576,9,0) -> #N/A
A56: 41185 | B56: 40794 | C56: ДНЕВНОЙ КРЕМ-КОМФОРТ NOVAGE SKINRELIEF PRO RESILIENT SPF 30 | D56: =VLOOKUP(A56,[2]Report!$1:$1048576,9,0) -> #N/A
A57: 41324 | B57: 35681 | C57: ПАРФЮМЕРНАЯ ВОДА AMBER ELIXIR MYSTERY | D57: =VLOOKUP(A57,[2]Report!$1:$1048576,9,0) -> #N/A
A58: 41377 | B58: 38382 | C58: ОЧИЩАЮЩАЯ ПЕНКА-КОМФОРТ ДЛЯ ЛИЦА NOVAGE SKINRELIEF PRO RESILIENT | D58: =VLOOKUP(A58,[2]Report!$1:$1048576,9,0) -> #N/A
A59: 41378 | B59: 38385 | C59: НОЧНОЙ КРЕМ-КОМФОРТ NOVAGE SKINRELIEF PRO RESILIENT | D59: =VLOOKUP(A59,[2]Report!$1:$1048576,9,0) -> #N/A
A60: 41379 | B60: 38390 | C60: КРЕМ-КОМФОРТ ДЛЯ КОЖИ ВОКРУГ ГЛАЗ NOVAGE SKINRELIEF PRO RESILIENT | D60: =VLOOKUP(A60,[2]Report!$1:$1048576,9,0) -> #N/A
A61: 41771 | B61: 42785 | C61: ТУАЛЕТНАЯ ВОДА LUCIA | D61: =VLOOKUP(A61,[2]Report!$1:$1048576,9,0) -> #N/A
A62: 42379 | B62: 40790 | C62: ТУАЛЕТНАЯ ВОДА ECLAT NUIT FOR HIM | D62: =VLOOKUP(A62,[2]Report!$1:$1048576,9,0) -> #N/A
A63: 42400 | B63: 38552 | C63: ТУАЛЕТНАЯ ВОДА GREATER FOR HIM | D63: =VLOOKUP(A63,[2]Report!$1:$1048576,9,0) -> #N/A
A64: 42438 | B64: 40788 | C64: ТУАЛЕТНАЯ ВОДА ECLAT NUIT FOR HER | D64: =VLOOKUP(A64,[2]Report!$1:$1048576,9,0) -> #N/A
A65: 42843 | B65: 41635 | C65: СТОЙКАЯ СУПЕРМАТОВАЯ ПОМАДА THE ONE COLOUR UNLIMITED - ЕСТЕСТВЕННЫЙ РОЗОВЫЙ | D65: =VLOOKUP(A65,[2]Report!$1:$1048576,9,0) -> #N/A
A66: 42844 | B66: 41636 | C66: - РОЗОВЫЙ БЕЖ | D66: =VLOOKUP(A66,[2]Report!$1:$1048576,9,0) -> #N/A
A67: 42845 | B67: 41637 | C67: - ТЁМНАЯ РОЗА | D67: =VLOOKUP(A67,[2]Report!$1:$1048576,9,0) -> #N/A
A68: 42846 | B68: 41638 | C68: - ШОКОЛАДНЫЙ ТРЮФЕЛЬ | D68: =VLOOKUP(A68,[2]Report!$1:$1048576,9,0) -> #N/A
A69: 42847 | B69: 41639 | C69: - МЯГКАЯ РОЗА | D69: =VLOOKUP(A69,[2]Report!$1:$1048576,9,0) -> #N/A
A70: 42848 | B70: 41640 | C70: - БАРХАТНЫЙ ЛИЛОВЫЙ | D70: =VLOOKUP(A70,[2]Report!$1:$1048576,9,0) -> #N/A
A71: 42849 | B71: 41641 | C71: - РОЗОВЫЙ КОРАЛЛ | D71: =VLOOKUP(A71,[2]Report!$1:$1048576,9,0) -> #N/A
A72: 42850 | B72: 41642 | C72: - КРАСНЫЙ РУБИН | D72: =VLOOKUP(A72,[2]Report!$1:$1048576,9,0) -> #N/A
... A74: 42852 | B74: 41644 | C74: - ТЁМНЫЙ ЯГОДНЫЙ | D74: =VLOOKUP(A74,[2]Report!$1:$1048576,9,0) -> #N/A
A75: 42934 | B75: =VLOOKUP(A75,'[3]02 КАТАЛОГ`24 (2)'!$1:$1048576,2,0) -> 40793 | C75: =VLOOKUP(A75,'[3]02 КАТАЛОГ`24 (2)'!$1:$1048576,3,0) -> ТУАЛЕТНАЯ ВОДА SIGNATURE GENERATION FOR HER | D75: =VLOOKUP(A75,[2]Report!$1:$1048576,9,0) -> #N/A
A76: 42994 | B76: =VLOOKUP(A76,'[3]02 КАТАЛОГ`24 (2)'!$1:$1048576,2,0) -> 42968 | C76: =VLOOKUP(A76,'[3]02 КАТАЛОГ`24 (2)'!$1:$1048576,3,0) -> ПАРФЮМЕРНАЯ ВОДА POSSESS ABSOLUTE | D76: =VLOOKUP(A76,[2]Report!$1:$1048576,9,0) -> #N/A
A77: 43145 | B77: 38948 | C77: МАТОВАЯ ГУБНАЯ ПОМАДА ONCOLOUR - МЯГКИЙ ПЕРСИК | D77: =VLOOKUP(A77,[2]Report!$1:$1048576,9,0) -> #N/A
A78: 43146 | B78: 39800 | C78: - НЮДОВЫЙ БЕЖ | D78: =VLOOKUP(A78,[2]Report!$1:$1048576,9,0) -> #N/A
A79: 43147 | B79: 39801 | C79: - НЕЖНЫЙ ЛИЛОВЫЙ | D79: =VLOOKUP(A79,[2]Report!$1:$1048576,9,0) -> #N/A
A80: 43148 | B80: 39802 | C80: - РОЗОВЫЙ КОРАЛЛ | D80: =VLOOKUP(A80,[2]Report!$1:$1048576,9,0) -> #N/A
A81: 43149 | B81: 39803 | C81: - РОЗОВАЯ ВСПЫШКА | D81: =VLOOKUP(A81,[2]Report!$1:$1048576,9,0) -> #N/A
A82: 43151 | B82: 39805 | C82: - СПЕЛАЯ СЛИВА | D82: =VLOOKUP(A82,[2]Report!$1:$1048576,9,0) -> #N/A
A83: 43152 | B83: 39806 | C83: - КРАСНЫЙ БАРХАТ | D83: =VLOOKUP(A83,[2]Report!$1:$1048576,9,0) -> #N/A
A84: 43153 | B84: 39807 | C84: - СТРАСТНЫЙ КРАСНЫЙ | D84: =VLOOKUP(A84,[2]Report!$1:$1048576,9,0) -> #N/A
A85: 43268 | B85: =VLOOKUP(A85,'[3]02 КАТАЛОГ`24 (2)'!$1:$1048576,2,0) -> 40797 | C85: =VLOOKUP(A85,'[3]02 КАТАЛОГ`24 (2)'!$1:$1048576,3,0) -> ТУАЛЕТНАЯ ВОДА SIGNATURE GENERATION FOR HIM | D85: =VLOOKUP(A85,[2]Report!$1:$1048576,9,0) -> #N/A
A86: 43395 | B86: 42324 | C86: САТИНОВАЯ ГУБНАЯ ПОМАДА GIORDANI GOLD ICONIC - КРЕМОВЫЙ БЕЖ | D86: =VLOOKUP(A86,[2]Report!$1:$1048576,9,0) -> #N/A
A87: 43396 | B87: 42325 | C87: - РОЗОВЫЙ НЮД | D87: =VLOOKUP(A87,[2]Report!$1:$1048576,9,0) -> #N/A
A88: 43397 | B88: 42326 | C88: - СЛИВОВЫЙ МАУВ | D88: =VLOOKUP(A88,[2]Report!$1:$1048576,9,0) -> #N/A
A89: 43398 | B89: 42327 | C89: - НЕЖНЫЙ ПИОН | D89: =VLOOKUP(A89,[2]Report!$1:$1048576,9,0) -> #N/A
A90: 43399 | B90: 42328 | C90: - СОЛНЕЧНЫЙ РОЗОВЫЙ | D90: =VLOOKUP(A90,[2]Report!$1:$1048576,9,0) -> #N/A
A91: 43400 | B91: 42329 | C91: - ЯРКАЯ ФУКСИЯ | D91: =VLOOKUP(A91,[2]Report!$1:$1048576,9,0) -> #N/A
A92: 43402 | B92: 42331 | C92: - КЛАССИЧЕСКИЙ КРАСНЫЙ | D92: =VLOOKUP(A92,[2]Report!$1:$1048576,9,0) -> #N/A
A93: 43403 | B93: 42332 | C93: - ГЛУБОКИЙ ВИННЫЙ | D93: =VLOOKUP(A93,[2]Report!$1:$1048576,9,0) -> #N/A
A94: 43888 | B94: 41044 | C94: ЛЕГКИЙ МУЛЬТИАКТИВНЫЙ ДНЕВНОЙ КРЕМ NOVAGE+ SPF 30 | D94: =VLOOKUP(A94,[2]Report!$1:$1048576,9,0) -> #N/A
A95: 43889 | B95: 41043 | C95: ЛЕГКИЙ ДНЕВНОЙ КРЕМ NOVAGE+ | D95: =VLOOKUP(A95,[2]Report!$1:$1048576,9,0) -> #N/A
A96: 43890 | B96: 41048 | C96: НАСЫЩЕННЫЙ МУЛЬТИАКТИВНЫЙ ДНЕВНОЙ КРЕМ NOVAGE+ SPF 30 | D96: =VLOOKUP(A96,[2]Report!$1:$1048576,9,0) -> #N/A
A97: 43891 | B97: 41047 | C97: НАСЫЩЕННЫЙ ДНЕВНОЙ КРЕМ NOVAGE+ | D97: =VLOOKUP(A97,[2]Report!$1:$1048576,9,0) -> #N/A
A98: 43892 | B98: 41033 | C98: КРЕМ ДЛЯ КОЖИ ВОКРУГ ГЛАЗ ПРОТИВ ПИГМЕНТАЦИИ NOVAGE+ BRIGHT INTENSE | D98: =VLOOKUP(A98,[2]Report!$1:$1048576,9,0) -> #N/A
A99: 43893 | B99: 41034 | C99: КРЕМ ДЛЯ КОЖИ ВОКРУГ ГЛАЗ ПРОТИВ МОРЩИН NOVAGE+ WRINKLE SMOOTH | D99: =VLOOKUP(A99,[2]Report!$1:$1048576,9,0) -> #N/A
A100: 43894 | B100: 42425 | C100: КРЕМ-ЛИФТИНГ ДЛЯ КОЖИ ВОКРУГ ГЛАЗ NOVAGE+ LIFT+ FIRM | D100: =VLOOKUP(A100,[2]Report!$1:$1048576,9,0) -> #N/A
A101: 43896 | B101: 41037 | C101: СЫВОРОТКА-ЛИФТИНГ ДЛЯ ЛИЦА NOVAGE+ LIFT + FIRM | D101: =VLOOKUP(A101,[2]Report!$1:$1048576,9,0) -> #N/A
A102: 43897 | B102: 41035 | C102: СЫВОРОТКА ДЛЯ ЛИЦА ПРОТИВ МОРЩИН NOVAGE+ WRINKLE SMOOTH | D102: =VLOOKUP(A102,[2]Report!$1:$1048576,9,0) -> #N/A
A103: 43898 | B103: 41040 | C103: СЫВОРОТКА ДЛЯ ЛИЦА ПРОТИВ ПИГМЕНТАЦИИ NOVAGE+ BRIGHT INTENSE | D103: =VLOOKUP(A103,[2]Report!$1:$1048576,9,0) -> #N/A
A104: 43899 | B104: 41039 | C104: АНТИВОЗРАСТНАЯ СЫВОРОТКА ДЛЯ ПРОБЛЕМНОЙ КОЖИ NOVAGE+ BLEMISH + AGE DEFY | D104: =VLOOKUP(A104,[2]Report!$1:$1048576,9,0) -> #N/A
A105: 43901 | B105: 41029 | C105: ОЧИЩАЮЩИЙ ГЕЛЬ ДЛЯ ЛИЦА NOVAGE+ | D105: =VLOOKUP(A105,[2]Report!$1:$1048576,9,0) -> #N/A
A106: 43902 | B106: 41032 | C106: ОЧИЩАЮЩЕЕ МАСЛО ДЛЯ ЛИЦА NOVAGE+ | D106: =VLOOKUP(A106,[2]Report!$1:$1048576,9,0) -> #N/A
A107: 43904 | B107: 41057 | C107: ЛЁГКИЙ МУЛЬТИАКТИВНЫЙ НОЧНОЙ КРЕМ NOVAGE+ | D107: =VLOOKUP(A107,[2]Report!$1:$1048576,9,0) -> #N/A
A108: 43905 | B108: 41058 | C108: НАСЫЩЕННЫЙ МУЛЬТИАКТИВНЫЙ НОЧНОЙ КРЕМ NOVAGE+ | D108: =VLOOKUP(A108,[2]Report!$1:$1048576,9,0) -> #N/A
A109: 43936 | B109: 38533 | C109: ПАРФЮМЕРНАЯ ВОДА GIORDANI GOLD GOOD AS GOLD | D109: =VLOOKUP(A109,[2]Report!$1:$1048576,9,0) -> #N/A
A110: 43937 | B110: 38538 | C110: ПАРФЮМЕРНАЯ ВОДА GIORDANI GOLD MAN | D110: =VLOOKUP(A110,[2]Report!$1:$1048576,9,0) -> #N/A
A111: 43938 | B111: 38531 | C111: ПАРФЮМЕРНАЯ ВОДА GIORDANI GOLD WOMAN | D111: =VLOOKUP(A111,[2]Report!$1:$1048576,9,0) -> #N/A
A112: 43968 | B112: 43118 | C112: ЖЕНСКАЯ ТУАЛЕТНАЯ ВОДА GREATER | D112: =VLOOKUP(A112,[2]Report!$1:$1048576,9,0) -> #N/A
...

Sheet 10 КАТАЛОГ`24 (3)
B1: ПРОДУКЦИЯ, НЕ ПРЕДСТАВЛЕННАЯ В КАТАЛОГЕ
A2: КОД | B2: НАИМЕНОВАНИЕ | C2: ББ | D2: ОП | E2: ПЦ
A3: 27730 | B3: ТОЧИЛКА ДЛЯ КАРАНДАШЕЙ | C3: 4 | D3: 119 | E3: 370
A4: 30399 | B4: ПАРФЮМЕРНАЯ ВОДА MISS GIORDANI | C4: 33 | D4: 2117 | E4: 3300
A5: 30468 | B5: ТУАЛЕТНАЯ ВОДА BE THE LEGEND | C5: 22 | D5: 1444 | E5: 2250
A6: 30888 | B6: КИСТЬ ДЛЯ ПУДРЫ И РУМЯН | C6: 14 | D6: 449 | E6: 1400
A7: 31603 | B7: ЖИДКОЕ МЫЛО ДЛЯ РУК MILK & HONEY GOLD | C7: 7 | D7: 481 | E7: 750
A8: 31698 | B8: ДЕЗОДОРАНТ-АНТИПЕРСПИРАНТ ДЛЯ ТЕЛА ECLAT HOMME | C8: 9 | D8: 609 | E8: 950
A9: 32438 | B9: ТУАЛЕТНАЯ ВОДА WOMEN'S COLLECTION WHITE LILAC | C9: 17 | D9: 1123 | E9: 1750
A10: 33027 | B10: КРЕМ ДЛЯ ЗАГРУБЕВШЕЙ КОЖИ НОГ FEET UP ADVANCED | C10: 9 | D10: 577 | E10: 900
A11: 33028 | B11: ИНТЕНСИВНО УВЛАЖНЯЮЩАЯ МАСКА ДЛЯ НОГ FEET UP ADVANCED | C11: 10 | D11: 642 | E11: 1000
A12: 33033 | B12: ОТШЕЛУШИВАЮЩИЙ КРЕМ ДЛЯ НОГ FEET UP ADVANCED | C12: 9 | D12: 577 | E12: 900
A13: 33034 | B13: ДЕЗОДОРАНТ-АНТИПЕРСПИРАНТ ДЛЯ НОГ 36-ЧАСОВОГО ДЕЙСТВИЯ FEET UP ADVANCED | C13: 12 | D13: 802 | E13: 1250
A14: 33139 | B14: ШАРИКОВЫЙ ДЕЗОДОРАНТ-АНТИПЕРСПИРАНТ С УХАЖИВАЮЩИМ КОМПЛЕКСОМ ACTIVELLE | C14: 5 | D14: 321 | E14: 500
... A330: 47507 | B330: ПОДВОДКА ДЛЯ ГЛАЗ THE ONE WONDER LINER - МОРОЗНЫЙ ИНЕЙ | C330: 12 | D330: 802 | E330: 1250

Sheet СПЕЦПРЕДЛОЖЕНИЯ
A1: КОД | B1: АКЦИЯ | C1: Наименование | D1: ББ | E1: ОП | F1: ПЦ
C2: предложение со стр. 9
A3: 47380 | C3: =VLOOKUP(A3,'10 КАТАЛОГ`24 (1)'!$1:$1048576,5,0) -> ЧАСЫ С РЕМЕШКОМ-ЛЕНТОЙ
A4: 1 | C4: ЦЕНА 1999 РУБ. ПРИ ЗАКАЗЕ НА 2000 РУБ. ИЗ ЭТОГО КАТАЛОГА ИЛИ НА САЙТЕ В ПЕРИОД ДЕЙСТВИЯ КАТАЛОГА (КРОМЕ 47380 И ПРОДУКТА ЗА ДОСТАВКУ)
C5: предложение со стр. 13
A6: 12760 | C6: =VLOOKUP(A6,'10 КАТАЛОГ`24 (1)'!$1:$1048576,5,0) -> СПЕЦИАЛЬНОЕ СМЯГЧАЮЩЕЕ СРЕДСТВО
A7: 36152 | C7: =VLOOKUP(A7,'10 КАТАЛОГ`24 (1)'!$1:$1048576,5,0) -> СПЕЦИАЛЬНОЕ СМЯГЧАЮЩЕЕ СРЕДСТВО С МАСЛОМ МАЛИНОВЫХ СЕМЯН
A8: 36153 | C8: =VLOOKUP(A8,'10 КАТАЛОГ`24 (1)'!$1:$1048576,5,0) -> СПЕЦИАЛЬНОЕ СМЯГЧАЮЩЕЕ СРЕДСТВО С МАСЛОМ МАРАКУЙИ
A9: 44398 | C9: =VLOOKUP(A9,'10 КАТАЛОГ`24 (1)'!$1:$1048576,5,0) -> СПЕЦИАЛЬНОЕ СМЯГЧАЮЩЕЕ СРЕДСТВО С МАСЛОМ СЕМЯН АРБУЗА
A10: 2 | C10: ПРИ ПОКУПКЕ ЛЮБЫХ ДВУХ СРЕДСТВ ЦЕНА КАЖДОГО 149 РУБ.
C11: предложение со стр. 32-33
A12: 38552 | C12: =VLOOKUP(A12,'10 КАТАЛОГ`24 (1)'!$1:$1048576,5,0) -> МУЖСКАЯ ТУАЛЕТНАЯ ВОДА GREATER
A13: 43118 | C13: =VLOOKUP(A13,'10 КАТАЛОГ`24 (1)'!$1:$1048576,5,0) -> ТУАЛЕТНАЯ ВОДА GREATER
A14: 3 | C14: ПРИ ПОКУПКЕ ЛЮБЫХ ДВУХ АРОМАТОВ ЦЕНА КАЖДОГО 1299 РУБ.
C15: предложение со стр. 34
A16: 41281 | C16: =VLOOKUP(A16,'10 КАТАЛОГ`24 (1)'!$1:$1048576,5,0) -> ОСВЕЖАЮЩЕЕ МЫЛО С ОРГАНИЧЕСКИМ ЗЕЛЁНЫМ ЧАЕМ И ОГУРЦОМ LOVE NATURE
A17: 47009 | C17: =VLOOKUP(A17,'10 КАТАЛОГ`24 (1)'!$1:$1048576,5,0) -> ГЕЛЬ ДЛЯ ДУША С ОРГАНИЧЕСКИМ АЛОЭ ВЕРА SIMPLE JOYS LOVE NATURE
A18: 44280 | C18: =VLOOKUP(A18,'10 КАТАЛОГ`24 (1)'!$1:$1048576,5,0) -> КРЕМ ДЛЯ РУК С ОРГАНИЧЕСКИМ МАСЛОМ АВОКАДО LOVE NATURE
A19: 150547 | C19: =VLOOKUP(A19,'10 КАТАЛОГ`24 (1)'!$1:$1048576,5,0) -> НАБОР ДЛЯ ТЕЛА LOVE NATURE
C20: предложение со стр. 35
A21: 41354 | C21: =VLOOKUP(A21,'10 КАТАЛОГ`24 (1)'!$1:$1048576,5,0) -> ШАМПУНЬ ДЛЯ ЖИРНЫХ ВОЛОС С ОРГАНИЧЕСКИМИ ЛИМОНОМ И МЯТОЙ LOVE NATURE
A22: 43253 | C22: =VLOOKUP(A22,'10 КАТАЛОГ`24 (1)'!$1:$1048576,5,0) -> СКРАБ-ШАМПУНЬ ДЛЯ ВОЛОС С УГЛЁМ И ОРГАНИЧЕСКОЙ МЯТОЙ LOVE NATURE
A23: 43661 | C23: =VLOOKUP(A23,'10 КАТАЛОГ`24 (1)'!$1:$1048576,5,0) -> УКРЕПЛЯЮЩАЯ МАСКА-СМУЗИ ДЛЯ ВОЛОС С ОРГАНИЧЕСКИМ БАНАНОМ LOVE NATURE
A24: 150548 | C24: =VLOOKUP(A24,'10 КАТАЛОГ`24 (1)'!$1:$1048576,5,0) -> НАБОР ДЛЯ ВОЛОС LOVE NATURE
C25: предложение со стр. 38
A26: 32139 | C26: =VLOOKUP(A26,'10 КАТАЛОГ`24 (1)'!$1:$1048576,5,0) -> СРЕДСТВО ДЛЯ СНЯТИЯ МАКИЯЖА THE ONE
A27: 4 | C27: ЦЕНА 399 РУБ. ПРИ ЗАКАЗЕ ЛЮБОЙ ПОМАДЫ СО СТР. 37-45

Sheet NOVAGE КАТАЛОГ
A1: КОД | B1: СКИДКА | C1: СТР. | D1: НАИМЕНОВАНИЕ | E1: ББ | F1: ОП | G1: ПЦ
A2: 34612 | C2: 1 | D2: УВЛАЖНЯЮЩИЙ ГЕЛЬ-КРЕМ ПРОТИВ СТАРЕНИЯ КОЖИ NOVAGE MEN | E2: - | F2: - | G2: 35
A3: 34613 | C3: 1 | D3: УВЛАЖНЯЮЩАЯ ЭНЕРГОСЫВОРОТКА ДЛЯ ЛИЦА NOVAGE MEN | E3: - | F3: - | G3: 35
A4: 35084 | C4: 1 | D4: ОЧИЩАЮЩИЙ ГЕЛЬ-ТОНИК ДЛЯ УМЫВАНИЯ NOVAGE (ПРОБНИК) | E4: - | F4: - | G4: 35
A5: 35198 | C5: 1 | D5: ОМОЛАЖИВАЮЩАЯ СЫВОРОТКА ДЛЯ ЛИЦА И ШЕИ NOVAGE TIME RESTORE (ПРОБНИК) | E5: - | F5: - | G5: 35
A6: 35200 | C6: 1 | D6: ОМОЛАЖИВАЮЩИЙ КРЕМ ДЛЯ КОНТУРА ГЛАЗ И ГУБ NOVAGE TIME RESTORE (ПРОБНИК) | E6: - | F6: - | G6: 35
A7: 35231 | C7: 1 | D7: СРЕДСТВО ДЛЯ УМЫВАНИЯ И СКРАБА 2-В-1 NOVAGE MEN (ПРОБНИК) | E7: - | F7: - | G7: 35
A8: 35232 | C8: 1 | D8: ТОНИЗИРУЮЩИЙ ГЕЛЬ ДЛЯ КОЖИ ВОКРУГ ГЛАЗ NOVAGE MEN (ПРОБНИК) | E8: - | F8: - | G8: 35
A9: 35332 | C9: 1 | D9: ОМОЛАЖИВАЮЩИЙ ДНЕВНОЙ КРЕМ SPF 15 NOVAGE TIME RESTORE (ПРОБНИК) | E9: - | F9: - | G9: 35
A10: 35333 | C10: 1 | D10: ОМОЛАЖИВАЮЩИЙ НОЧНОЙ КРЕМ NOVAGE TIME RESTORE (ПРОБНИК) | E10: - | F10: - | G10: 35
A11: 41183 | C11: 1 | D11: СЫВОРОТКА-КОМФОРТ ДЛЯ ЛИЦА NOVAGE SKINRELIEF PRO RESILIENT (ПРОБНИК) | E11: - | F11: - | G11: 35
A12: 41185 | C12: 1 | D12: ДНЕВНОЙ КРЕМ-КОМФОРТ NOVAGE SKINRELIEF PRO RESILIENT SPF 30 (ПРОБНИК) | E12: - | F12: - | G12: 35
A13: 41377 | C13: 1 | D13: ОЧИЩАЮЩАЯ ПЕНКА-КОМФОРТ ДЛЯ ЛИЦА NOVAGE SKINRELIEF PRO RESILIENT (ПРОБНИК) | E13: - | F13: - | G13: 35
... A33: 46211 | C33: 1 | D33: МАСКА ДЛЯ ЛИЦА С ЭФФЕКТОМ ПИЛИНГА WAUNT (ПРОБНИК) | E33: - | F33: - | G33: 35
A34: 29446 | B34: 0.30401961 | C34: 2 | D34: КОМПЛЕКСНЫЙ УХОД ДЛЯ МУЖСКОЙ КОЖИ NOVAGE MEN | E34: 85 | F34: 4555 | G34: 7099
A35: 31774 | B35: 0.30076923 | C35: 2 | D35: КОМПЛЕКСНЫЙ ОМОЛАЖИВАЮЩИЙ УХОД NOVAGE TIME RESTORE | E35: 120 | F35: 6416 | G35: 9999
A36: 32629 | B36: 0.3604 | C36: 1 | D36: ОМОЛАЖИВАЮЩИЙ КРЕМ ДЛЯ КОНТУРА ГЛАЗ И ГУБ NOVAGE TIME RESTORE | E36: 16 | F36: 1026 | G36: 1599
A37: 32630 | B37: 0.35025 | C37: 1 | D37: ОМОЛАЖИВАЮЩАЯ СЫВОРОТКА ДЛЯ ЛИЦА И ШЕИ NOVAGE TIME RESTORE | E37: 26 | F37: 1668 | G37: 2599
A38: 33199 | B38: 0.34826087 | C38: 1 | D38: ТОНИЗИРУЮЩИЙ ГЕЛЬ ДЛЯ КОЖИ ВОКРУГ ГЛАЗ NOVAGE MEN | E38: 15 | F38: 962 | G38: 1499
A39: 33200 | B39: 0.35162162 | C39: 1 | D39: УВЛАЖНЯЮЩАЯ ЭНЕРГОСЫВОРОТКА ДЛЯ ЛИЦА NOVAGE MEN | E39: 24 | F39: 1539 | G39: 2399
A40: 38390 | B40: 0.34826087 | C40: 1 | D40: КРЕМ-КОМФОРТ ДЛЯ КОЖИ ВОКРУГ ГЛАЗ NOVAGE SKINRELIEF PRO RESILIENT | E40: 15 | F40: 962 | G40: 1499
A41: 38391 | B41: 0.35162162 | C41: 1 | D41: СЫВОРОТКА-КОМФОРТ ДЛЯ ЛИЦА NOVAGE SKINRELIEF PRO RESILIENT | E41: 24 | F41: 1539 | G41: 2399
A42: 41033 | B42: 0.3604 | C42: 1 | D42: КРЕМ ДЛЯ КОЖИ ВОКРУГ ГЛАЗ ПРОТИВ ПИГМЕНТАЦИИ NOVAGE+ BRIGHT INTENSE | E42: 16 | F42: 1026 | G42: 1599
A43: 41034 | B43: 0.3604 | C43: 1 | D43: КРЕМ ДЛЯ КОЖИ ВОКРУГ ГЛАЗ ПРОТИВ МОРЩИН NOVAGE+ WRINKLE SMOOTH | E43: 16 | F43: 1026 | G43: 1599
A44: 41035 | B44: 0.35025 | C44: 1 | D44: СЫВОРОТКА ДЛЯ ЛИЦА ПРОТИВ МОРЩИН NOVAGE+ WRINKLE SMOOTH | E44: 26 | F44: 1668 | G44: 2599
A45: 41037 | B45: 0.35025 | C45: 1 | D45: СЫВОРОТКА-ЛИФТИНГ ДЛЯ ЛИЦА NOVAGE+ LIFT + FIRM | E45: 26 | F45: 1668 | G45: 2599
... A53: 45608 | B53: 0.30076923 | C53: 2 | D53: КОМПЛЕКСНЫЙ АНТИВОЗРАСТНОЙ УХОД ДЛЯ ПРОБЛЕМНОЙ КОЖИ NOVAGE+ BLEMISH + AGE DEFY | E53: 120 | F53: 6416 | G53: 9999
A54: 545710 | C54: 2 | D54: НАБОР ПРОБНИКОВ NOVAGE MEN | E54: - | F54: - | G54: 140
A55: 545710 | B55: 0.29 | C55: 2 | D55: НАБОР ПРОБНИКОВ NOVAGE MEN | E55: - | F55: - | G55: 495
A56: 545784 | C56: 2 | D56: НАБОР ПРОБНИКОВ NOVAGE TIME RESTORE | E56: - | F56: - | G56: 175
A57: 545784 | B57: 0.32 | C57: 2 | D57: НАБОР ПРОБНИКОВ NOVAGE TIME RESTORE | E57: - | F57: - | G57: 595
A58: 548043 | C58: 2 | D58: НАБОР ПРОБНИКОВ NOVAGE SKINRELIEF | E58: - | F58: - | G58: 175
A59: 548043 | B59: 0.32 | C59: 2 | D59: НАБОР ПРОБНИКОВ NOVAGE SKINRELIEF | E59: - | F59: - | G59: 595
A60: 548052 | C60: 2 | D60: НАБОР ПРОБНИКОВ NOVAGE 3.0 LIFTING | E60: - | F60: - | G60: 175
A61: 548052 | B61: 0.32 | C61: 2 | D61: НАБОР ПРОБНИКОВ NOVAGE 3.0 LIFTING | E61: - | F61: - | G61: 595
A62: 548053 | C62: 2 | D62: НАБОР ПРОБНИКОВ NOVAGE 3.0 BRIGHTENING | E62: - | F62: - | G62: 175
A63: 548053 | B63: 0.32 | C63: 2 | D63: НАБОР ПРОБНИКОВ NOVAGE 3.0 BRIGHTENING | E63: - | F63: - | G63: 595
A64: 548054 | C64: 2 | D64: НАБОР ПРОБНИКОВ NOVAGE 3.0 ANTI-ACNE | E64: - | F64: - | G64: 175
A65: 548054 | B65: 0.32 | C65: 2 | D65: НАБОР ПРОБНИКОВ NOVAGE 3.0 ANTI-ACNE | E65: - | F65: - | G65: 595
A66: 548268 | B66: 0.32 | C66: 2 | D66: НАБОР ПРОБНИКОВ NOVAGE 3.0 WRINKLE | E66: - | F66: - | G66: 595

Sheet КАТАЛОГ WELLOSOPHY
A1: КОД | B1: СКИДКА | C1: СТР. | D1: НАИМЕНОВАНИЕ | E1: ББ | F1: ОП | G1: ПЦ
A2: 22467 | C2: 5 | D2: "ОМЕГА-3" ДЛЯ ДЕТЕЙ | E2: 24 | F2: 1475 | G2: 2300
A3: 27996 | C3: 4 | D3: КОМПЛЕКС "МУЛЬТИВИТАМИНЫ И МИНЕРАЛЫ" ДЛЯ ДЕТЕЙ | E3: 17 | F3: 1090 | G3: 1700
A4: 29695 | C4: 7 | D4: СУП «НЭЧУРАЛ БАЛАНС» - СПАРЖА | E4: 52 | F4: 3208 | G4: 5000
A5: 29706 | C5: 10 | D5: НУТРИКОМПЛЕКС ДЛЯ ВОЛОС И НОГТЕЙ | E5: 29 | F5: 1797 | G5: 2800
A6: 31750 | C6: 3 | D6: ПРЕБИОТИЧЕСКИЙ НАПИТОК С ПИЩЕВЫМИ ВОЛОКНАМИ | E6: 24 | F6: 1475 | G6: 2300
A7: 37285 | C7: 1 | D7: СУХАЯ СМЕСЬ ДЛЯ КОКТЕЙЛЯ «НЭЧУРАЛ БАЛАНС» - КЛУБНИЧНЫЙ ВКУС | E7: 52 | F7: 3208 | G7: 5000
A8: 37289 | C8: 11 | D8: СУХАЯ СМЕСЬ ДЛЯ КОКТЕЙЛЯ «НЭЧУРАЛ БАЛАНС» - ШОКОЛАДНЫЙ ВКУС | E8: 52 | F8: 3208 | G8: 5000
A9: 37290 | C9: 11 | D9: СУХАЯ СМЕСЬ ДЛЯ КОКТЕЙЛЯ «НЭЧУРАЛ БАЛАНС» - ВАНИЛЬНЫЙ ВКУС | E9: 52 | F9: 3208 | G9: 5000
A10: 37293 | C10: 2 | D10: ПРОТЕИНОВЫЙ КОМПЛЕКС | E10: 52 | F10: 3208 | G10: 5000
A11: 38556 | C11: 1 | D11: КОМПЛЕКС «ОМЕГА-3» | E11: 24 | F11: 1475 | G11: 2300
A12: 38557 | C12: 1 | D12: КОМПЛЕКС «АСТАКСАНТИН И ЭКСТРАКТ ЧЕРНИКИ» | E12: 29 | F12: 1797 | G12: 2800
A13: 38558 | C13: 1 | D13: КОМПЛЕКС «МУЛЬТИВИТАМИНЫ И МИНЕРАЛЫ» ДЛЯ МУЖЧИН | E13: 29 | F13: 1797 | G13: 2800
... A24: 47417 | C24: 1 | D24: ШЕЙКЕР | E24: 10 | F24: 321 | G24: 999

Sheet ПРОДУКТ ЗА ДОСТАВКУ
A1: КОД | B1: СКИДКА | C1: СТР. | D1: НАИМЕНОВАНИЕ | E1: ББ | F1: ОП | G1: ПЦ
