Workbook

Sheet КАЛЬКУЛЯТОР
A1: КОД | B1: КОЛ-ВО | C1: СКИДКА | D1: НАИМЕНОВАНИЕ | E1: ББ | F1: ОП | G1: ПЦ
D2: С У М М А | E2: =SUM(E3:E900) -> 0 | F2: =SUM(F3:F900) -> 0 | G2: =SUM(G3:G900) -> 0
C3: =IF(A3=""," ",VLOOKUP(A3,'18.11-07.12.2024'!A:H,2,FALSE)) | D3: =IF(A3=""," ",VLOOKUP(A3,'18.11-07.12.2024'!A:H,5,FALSE)) | E3: =IF(A3=""," ",B3*VLOOKUP(A3,'18.11-07.12.2024'!A:H,6,FALSE)) | F3: =IF(A3=""," ",B3*VLOOKUP(A3,'18.11-07.12.2024'!A:H,7,FALSE)) | G3: =IF(A3=""," ",B3*VLOOKUP(A3,'18.11-07.12.2024'!A:H,8,FALSE))
C4: =IF(A4=""," ",VLOOKUP(A4,'18.11-07.12.2024'!A:H,2,FALSE)) | D4: =IF(A4=""," ",VLOOKUP(A4,'18.11-07.12.2024'!A:H,5,FALSE)) | E4: =IF(A4=""," ",B4*VLOOKUP(A4,'18.11-07.12.2024'!A:H,6,FALSE)) | F4: =IF(A4=""," ",B4*VLOOKUP(A4,'18.11-07.12.2024'!A:H,7,FALSE)) | G4: =IF(A4=""," ",B4*VLOOKUP(A4,'18.11-07.12.2024'!A:H,8,FALSE))
C5: =IF(A5=""," ",VLOOKUP(A5,'18.11-07.12.2024'!A:H,2,FALSE)) | D5: =IF(A5=""," ",VLOOKUP(A5,'18.11-07.12.2024'!A:H,5,FALSE)) | E5: =IF(A5=""," ",B5*VLOOKUP(A5,'18.11-07.12.2024'!A:H,6,FALSE)) | F5: =IF(A5=""," ",B5*VLOOKUP(A5,'18.11-07.12.2024'!A:H,7,FALSE)) | G5: =IF(A5=""," ",B5*VLOOKUP(A5,'18.11-07.12.2024'!A:H,8,FALSE))
C6: =IF(A6=""," ",VLOOKUP(A6,'18.11-07.12.2024'!A:H,2,FALSE)) | D6: =IF(A6=""," ",VLOOKUP(A6,'18.11-07.12.2024'!A:H,5,FALSE)) | E6: =IF(A6=""," ",B6*VLOOKUP(A6,'18.11-07.12.2024'!A:H,6,FALSE)) | F6: =IF(A6=""," ",B6*VLOOKUP(A6,'18.11-07.12.2024'!A:H,7,FALSE)) | G6: =IF(A6=""," ",B6*VLOOKUP(A6,'18.11-07.12.2024'!A:H,8,FALSE))
C7: =IF(A7=""," ",VLOOKUP(A7,'18.11-07.12.2024'!A:H,2,FALSE)) | D7: =IF(A7=""," ",VLOOKUP(A7,'18.11-07.12.2024'!A:H,5,FALSE)) | E7: =IF(A7=""," ",B7*VLOOKUP(A7,'18.11-07.12.2024'!A:H,6,FALSE)) | F7: =IF(A7=""," ",B7*VLOOKUP(A7,'18.11-07.12.2024'!A:H,7,FALSE)) | G7: =IF(A7=""," ",B7*VLOOKUP(A7,'18.11-07.12.2024'!A:H,8,FALSE))
C8: =IF(A8=""," ",VLOOKUP(A8,'18.11-07.12.2024'!A:H,2,FALSE)) | D8: =IF(A8=""," ",VLOOKUP(A8,'18.11-07.12.2024'!A:H,5,FALSE)) | E8: =IF(A8=""," ",B8*VLOOKUP(A8,'18.11-07.12.2024'!A:H,6,FALSE)) | F8: =IF(A8=""," ",B8*VLOOKUP(A8,'18.11-07.12.2024'!A:H,7,FALSE)) | G8: =IF(A8=""," ",B8*VLOOKUP(A8,'18.11-07.12.2024'!A:H,8,FALSE))
C9: =IF(A9=""," ",VLOOKUP(A9,'18.11-07.12.2024'!A:H,2,FALSE)) | D9: =IF(A9=""," ",VLOOKUP(A9,'18.11-07.12.2024'!A:H,5,FALSE)) | E9: =IF(A9=""," ",B9*VLOOKUP(A9,'18.11-07.12.2024'!A:H,6,FALSE)) | F9: =IF(A9=""," ",B9*VLOOKUP(A9,'18.11-07.12.2024'!A:H,7,FALSE)) | G9: =IF(A9=""," ",B9*VLOOKUP(A9,'18.11-07.12.2024'!A:H,8,FALSE))
C10: =IF(A10=""," ",VLOOKUP(A10,'18.11-07.12.2024'!A:H,2,FALSE)) | D10: =IF(A10=""," ",VLOOKUP(A10,'18.11-07.12.2024'!A:H,5,FALSE)) | E10: =IF(A10=""," ",B10*VLOOKUP(A10,'18.11-07.12.2024'!A:H,6,FALSE)) | F10: =IF(A10=""," ",B10*VLOOKUP(A10,'18.11-07.12.2024'!A:H,7,FALSE)) | G10: =IF(A10=""," ",B10*VLOOKUP(A10,'18.11-07.12.2024'!A:H,8,FALSE))
C11: =IF(A11=""," ",VLOOKUP(A11,'18.11-07.12.2024'!A:H,2,FALSE)) | D11: =IF(A11=""," ",VLOOKUP(A11,'18.11-07.12.2024'!A:H,5,FALSE)) | E11: =IF(A11=""," ",B11*VLOOKUP(A11,'18.11-07.12.2024'!A:H,6,FALSE)) | F11: =IF(A11=""," ",B11*VLOOKUP(A11,'18.11-07.12.2024'!A:H,7,FALSE)) | G11: =IF(A11=""," ",B11*VLOOKUP(A11,'18.11-07.12.2024'!A:H,8,FALSE))
C12: =IF(A12=""," ",VLOOKUP(A12,'18.11-07.12.2024'!A:H,2,FALSE)) | D12: =IF(A12=""," ",VLOOKUP(A12,'18.11-07.12.2024'!A:H,5,FALSE)) | E12: =IF(A12=""," ",B12*VLOOKUP(A12,'18.11-07.12.2024'!A:H,6,FALSE)) | F12: =IF(A12=""," ",B12*VLOOKUP(A12,'18.11-07.12.2024'!A:H,7,FALSE)) | G12: =IF(A12=""," ",B12*VLOOKUP(A12,'18.11-07.12.2024'!A:H,8,FALSE))
C13: =IF(A13=""," ",VLOOKUP(A13,'18.11-07.12.2024'!A:H,2,FALSE)) | D13: =IF(A13=""," ",VLOOKUP(A13,'18.11-07.12.2024'!A:H,5,FALSE)) | E13: =IF(A13=""," ",B13*VLOOKUP(A13,'18.11-07.12.2024'!A:H,6,FALSE)) | F13: =IF(A13=""," ",B13*VLOOKUP(A13,'18.11-07.12.2024'!A:H,7,FALSE)) | G13: =IF(A13=""," ",B13*VLOOKUP(A13,'18.11-07.12.2024'!A:H,8,FALSE))
C14: =IF(A14=""," ",VLOOKUP(A14,'18.11-07.12.2024'!A:H,2,FALSE)) | D14: =IF(A14=""," ",VLOOKUP(A14,'18.11-07.12.2024'!A:H,5,FALSE)) | E14: =IF(A14=""," ",B14*VLOOKUP(A14,'18.11-07.12.2024'!A:H,6,FALSE)) | F14: =IF(A14=""," ",B14*VLOOKUP(A14,'18.11-07.12.2024'!A:H,7,FALSE)) | G14: =IF(A14=""," ",B14*VLOOKUP(A14,'18.11-07.12.2024'!A:H,8,FALSE))
... C876: =IF(A876=""," ",VLOOKUP(A876,'18.11-07.12.2024'!A:H,2,FALSE)) | D876: =IF(A876=""," ",VLOOKUP(A876,'18.11-07.12.2024'!A:H,5,FALSE)) | E876: =IF(A876=""," ",B876*VLOOKUP(A876,'18.11-07.12.2024'!A:H,6,FALSE)) | F876: =IF(A876=""," ",B876*VLOOKUP(A876,'18.11-07.12.2024'!A:H,7,FALSE)) | G876: =IF(A876=""," ",B876*VLOOKUP(A876,'18.11-07.12.2024'!A:H,8,FALSE))

Sheet 18.11-07.12.2024
A1: КОД | B1: СКИДКА | C1: СТР. | D1: АКЦИЯ | E1: НАИМЕНОВАНИЕ | F1: ББ | G1: ОП | H1: ПЦ
A2: НОВИНКИ
A3: 46055 | C3: 52 | E3: МУЖСКИЕ ДУХИ GIORDANI GOLD ESSENZA ELIXIR (ПРОБНИК) | F3: 0 | G3: 0 | H3: 35
A4: 46069 | B4: 0.50083333 | C4: 23 | E4: НАБОР СПЕЦИАЛЬНЫХ СМЯГЧАЮЩИХ СРЕДСТВ | F4: 6 | G4: 384 | H4: 599
A5: 46607 | B5: 0.4568 | C5: 5 | E5: КРЕМОВАЯ ГУБНАЯ ПОМАДА С БЛЕСТЯЩИМ СТЕРЖНЕМ THE ONE - НЕПОВТОРИМЫЙ НЮД | F5: 7 | G5: 436 | H5: 679
A6: 46608 | B6: 0.4568 | C6: 5 | E6: - ВПЕЧАТЛЯЮЩИЙ РОЗОВЫЙ | F6: 7 | G6: 436 | H6: 679
A7: 46609 | B7: 0.4568 | C7: 5 | E7: - АЛЫЙ РУБИН | F7: 7 | G7: 436 | H7: 679
A8: 46642 | B8: 0.4408 | C8: 21 | E8: ЖИДКОЕ МЫЛО ДЛЯ РУК И ТЕЛА С ЛИМОНОМ И ВЕРБЕНОЙ ESSENSE & CO. | F8: 7 | G8: 449 | H8: 699
A9: 46643 | B9: 0.450625 | C9: 21 | E9: ЛОСЬОН ДЛЯ РУК И ТЕЛА С ЛИМОНОМ И ВЕРБЕНОЙ ESSENSE & CO. | F9: 9 | G9: 564 | H9: 879
A10: 46705 | B10: 0.40181818 | C10: 11 | E10: ГЕЛЬ-ЛАК ДЛЯ НОГТЕЙ THE ONE - ГЛАМУРНЫЙ ЗЕЛЁНЫЙ | F10: 3 | G10: 211 | H10: 329
A11: 46706 | B11: 0.40181818 | C11: 11 | E11: - ЭФФЕКТНЫЙ РОЗОВЫЙ | F11: 3 | G11: 211 | H11: 329
A12: 46707 | B12: 0.40181818 | C12: 11 | E12: - ВЛАСТНЫЙ КРАСНЫЙ | F12: 3 | G12: 211 | H12: 329
A13: 46708 | B13: 0.40181818 | C13: 11 | E13: - ЗАГАДОЧНЫЙ БРОНЗОВЫЙ | F13: 3 | G13: 211 | H13: 329
A14: 46731 | B14: 0.44428571 | C14: 21 | E14: ЖИДКОЕ МЫЛО ДЛЯ РУК И ТЕЛА С ЛИМОНОМ И ВЕРБЕНОЙ ESSENSE & CO. (РЕФИЛ) | F14: 4 | G14: 249 | H14: 389
A15: 47012 | B15: 0.34869565 | C15: 47 | E15: ПАРФЮМИРОВАННЫЙ КРЕМ ДЛЯ ТЕЛА AMBER ELIXIR | F15: 7 | G15: 480 | H15: 749
... A24: 47543 | B24: 0.44814815 | C24: 144 | E24: МОЧАЛКА ДЛЯ ДУША | F24: 1 | G24: 48 | H24: 149
A25: 47550 | C25: 13 | E25: НАБОР КИСТЕЙ ДЛЯ МАКИЯЖА | F25: 16 | G25: 513 | H25: 1600
A26: 47551 | B26: 0.39508197 | C26: 10 | E26: СИЛИКОНОВЫЙ СПОНЖ ДЛЯ МАКИЯЖА | F26: 4 | G26: 118 | H26: 369
A27: 47552 | B27: 0.3604 | C27: 10 | E27: КОСМЕТИЧКА | F27: 16 | G27: 513 | H27: 1599
A28: 47554 | B28: 0.40810811 | C28: 10 | E28: НАБОР ПИЛОК ДЛЯ НОГТЕЙ | F28: 2 | G28: 70 | H28: 219
A29: 47628 | C29: 15 | E29: ЧАСЫ С ИЗУМРУДНЫМ ЦИФЕРБЛАТОМ | F29: 30 | G29: 962 | H29: 2999
A30: 47630 | C30: 16 | E30: СЕРЬГИ-ГВОЗДИКИ С ИЗУМРУДНЫМИ КРИСТАЛЛАМИ | F30: 13 | G30: 417 | H30: 1299
A31: 47631 | C31: 16 | E31: КОЛЬЕ-ЦЕПОЧКА С ИЗУМРУДНЫМИ КРИСТАЛЛАМИ | F31: 16 | G31: 513 | H31: 1599
A32: 47650 | C32: 14 | E32: СУМКА С БАНТОМ НА ЦЕПОЧКЕ | F32: 25 | G32: 802 | H32: 2499
A33: 47652 | C33: 14 | E33: НАБОР ЗАКОЛОК ДЛЯ ВОЛОС | F33: 9 | G33: 288 | H33: 899
A34: 47654 | C34: 14 | E34: ОБОДОК ДЛЯ ВОЛОС СО СТРАЗАМИ | F34: 10 | G34: 321 | H34: 999
A35: 47662 | C35: 17 | E35: НАБОР УКРАШЕНИЙ С НАТУРАЛЬНОЙ ШПИНЕЛЬЮ | F35: 15 | G35: 481 | H35: 1499
A36: 150838 | B36: 0.44862069 | C36: 29 | E36: НОЧНАЯ МАСКА ДЛЯ ИНТЕНСИВНОГО ВОССТАНОВЛЕНИЯ КОЖИ NOVAGE+. ПРАЗДНИЧНЫЙ ВЫПУСК | F36: 16 | G36: 1026 | H36: 1599
A37: КАТАЛОГ
E38: WELLOSOPHY
A39: 29699 | B39: 0.2005 | C39: 97 | E39: КОМПЛЕКС «МУЛЬТИВИТАМИНЫ И МИНЕРАЛЫ» ДЛЯ ДЕТЕЙ | F39: 16 | G39: 1026 | H39: 1599
A40: 29695 | C40: 94 | E40: СУП «НЭЧУРАЛ БАЛАНС» - СПАРЖА | F40: 52 | G40: 3208 | H40: 5000
A41: 37285 | C41: 95 | E41: СУХАЯ СМЕСЬ ДЛЯ КОКТЕЙЛЯ «НЭЧУРАЛ БАЛАНС» - КЛУБНИЧНЫЙ ВКУС | F41: 52 | G41: 3208 | H41: 5000
A42: 37289 | C42: 95 | E42: СУХАЯ СМЕСЬ ДЛЯ КОКТЕЙЛЯ «НЭЧУРАЛ БАЛАНС» - ШОКОЛАДНЫЙ ВКУС | F42: 52 | G42: 3208 | H42: 5000
A43: 37290 | C43: 95 | E43: СУХАЯ СМЕСЬ ДЛЯ КОКТЕЙЛЯ «НЭЧУРАЛ БАЛАНС» - ВАНИЛЬНЫЙ ВКУС | F43: 52 | G43: 3208 | H43: 5000
A44: 37293 | C44: 94 | E44: ПРОТЕИНОВЫЙ КОМПЛЕКС | F44: 52 | G44: 3208 | H44: 5000
A45: 38556 | C45: 90 | E45: КОМПЛЕКС «ОМЕГА-3» | F45: 24 | G45: 1475 | H45: 2300
A46: 38557 | B46: 0.39321429 | C46: 89 | E46: КОМПЛЕКС «АСТАКСАНТИН И ЭКСТРАКТ ЧЕРНИКИ» | F46: 18 | G46: 1090 | H46: 1699
A47: 38558 | C47: 91 | E47: КОМПЛЕКС «МУЛЬТИВИТАМИНЫ И МИНЕРАЛЫ» ДЛЯ МУЖЧИН | F47: 29 | G47: 1797 | H47: 2800
A48: 38559 | C48: 91 | E48: КОМПЛЕКС «МУЛЬТИВИТАМИНЫ И МИНЕРАЛЫ» ДЛЯ ЖЕНЩИН | F48: 29 | G48: 1797 | H48: 2800
A49: 38836 | C49: 96 | E49: WELLOSOPHY WELLNESS PACK ДЛЯ МУЖЧИН | F49: 50 | G49: 2887 | H49: 4500
A50: 38838 | C50: 96 | E50: WELLOSOPHY WELLNESS PACK ДЛЯ ЖЕНЩИН | F50: 50 | G50: 2887 | H50: 4500
A51: 40745 | C51: 94 | E51: ПИТАТЕЛЬНЫЙ СУП ДЛЯ КОНТРОЛЯ ВЕСА - ГРИБНОЙ ВКУС | F51: 70 | G51: 3850 | H51: 6000
A52: 45148 | C52: 126 | E52: БАЛЬЗАМ ДЛЯ КОЖИ ВОКРУГ ГЛАЗ WELLOSOPHY - УВЛАЖНЕНИЕ И ВОССТАНОВЛЕНИЕ | F52: 18 | G52: 1155 | H52: 1800
A53: 45149 | C53: 126 | E53: ОЧИЩАЮЩЕЕ СРЕДСТВО ДЛЯ ЛИЦА WELLOSOPHY - СИЯНИЕ И БАЛАНС | F53: 13 | G53: 834 | H53: 1300
A54: 45152 | B54: 0.251 | C54: 101 | E54: МАСКА ДЛЯ ЛИЦА WELLOSOPHY - ОТШЕЛУШИВАНИЕ И ТОНИЗИРОВАНИЕ | F54: 7 | G54: 480 | H54: 749
A55: 45273 | C55: 92 | E55: НУТРИКОМПЛЕКС ДЛЯ КОЖИ, ВОЛОС И НОГТЕЙ | F55: 35 | G55: 2245 | H55: 3500
A56: 45289 | B56: 0.24206897 | C56: 126 | E56: НОЧНОЙ ЭЛИКСИР WELLOSOPHY - ВОССТАНОВЛЕНИЕ И РАЗГЛАЖИВАНИЕ | F56: 11 | G56: 705 | H56: 1099
A57: 45290 | C57: 126 | E57: МИСТ ДЛЯ ЛИЦА WELLOSOPHY - ВОССТАНОВЛЕНИЕ И УВЛАЖНЕНИЕ | F57: 13 | G57: 834 | H57: 1300
A58: 45306 | C58: 94 | E58: ПИТАТЕЛЬНЫЙ КОКТЕЙЛЬ ДЛЯ КОНТРОЛЯ ВЕСА - ВАНИЛЬНЫЙ ВКУС | F58: 70 | G58: 3850 | H58: 6000
A59: 45307 | C59: 94 | E59: ПИТАТЕЛЬНЫЙ КОКТЕЙЛЬ ДЛЯ КОНТРОЛЯ ВЕСА - ШОКОЛАДНЫЙ ВКУС | F59: 70 | G59: 3850 | H59: 6000
A60: 45309 | C60: 90 | E60: КОМПЛЕКС "МОРСКОЙ КАЛЬЦИЙ И ВИТАМИН D" | F60: 24 | G60: 1475 | H60: 2300
A61: 45312 | B61: 0.21782609 | C61: 93 | E61: ПРЕБИОТИЧЕСКИЙ НАПИТОК С ПИЩЕВЫМИ ВОЛОКНАМИ | F61: 18 | G61: 1154 | H61: 1799
A62: 46068 | C62: 94 | E62: МЕРНАЯ ЛОЖКА | F62: 1 | G62: 38 | H62: 119
A63: 46661 | B63: 0.27808676 | C63: 126 | E63: СКРЕБОК ГУАША ДЛЯ ЛИЦА | F63: 6 | G63: 208 | H63: 649
A64: 46685 | C64: 92 | E64: ОХЛАЖДАЮЩЕЕ ПОЛОТЕНЦЕ | F64: 7 | G64: 224 | H64: 699
A65: 47417 | C65: 95 | E65: ШЕЙКЕР | F65: 10 | G65: 321 | H65: 999
A66: 47555 | C66: 94 | E66: НАБОР КОНТЕЙНЕРОВ | F66: 9 | G66: 288 | H66: 899
A67: 47785 | B67: 0.2977381 | C67: 127 | E67: БАЗОВЫЙ НАБОР ДЛЯ УХОДА ЗА КОЖЕЙ WELLOSOPHY + КОМПЛЕКС «АСТАКСАНТИН И ЭКСТРАКТ ЧЕРНИКИ | F67: 71 | G67: 3785 | H67: 5899
E68: ДЕКОРАТИВНАЯ КОСМЕТИКА
E69: ПОМАДЫ, БЛЕСКИ И КАРАНДАШИ ДЛЯ ГУБ
A70: 37728 | B70: 0.402 | C70: 81 | E70: КАРАНДАШ ДЛЯ ГУБ THE ONE - НЮД | F70: 3 | G70: 192 | H70: 299
A71: 37729 | B71: 0.402 | C71: 81 | E71: - КАРАМЕЛЬ | F71: 3 | G71: 192 | H71: 299
A72: 37730 | B72: 0.402 | C72: 81 | E72: - ПЫЛЬНАЯ РОЗА | F72: 3 | G72: 192 | H72: 299
A73: 37731 | B73: 0.402 | C73: 81 | E73: - РОЗОВЫЙ | F73: 3 | G73: 192 | H73: 299
A74: 37734 | B74: 0.402 | C74: 81 | E74: - КРАСНЫЙ | F74: 3 | G74: 192 | H74: 299
A75: 37735 | B75: 0.402 | C75: 81 | E75: - ВИННЫЙ | F75: 3 | G75: 192 | H75: 299
A76: 37736 | B76: 0.402 | C76: 81 | E76: - СЛИВОВЫЙ | F76: 3 | G76: 192 | H76: 299
A77: 37737 | B77: 0.402 | C77: 81 | E77: - ШОКОЛАДНЫЙ | F77: 3 | G77: 192 | H77: 299
A78: 38742 | B78: 0.52291667 | C78: 85 | E78: КРЕМОВАЯ ГУБНАЯ ПОМАДА ONCOLOUR - РОЗОВЫЙ НЮД | F78: 2 | G78: 147 | H78: 229
A79: 38743 | B79: 0.52291667 | C79: 85 | E79: - ПЕРСИКОВЫЙ НЮД | F79: 2 | G79: 147 | H79: 229
A80: 38744 | B80: 0.52291667 | C80: 85 | E80: - МЕДОВЫЙ БЕЖ | F80: 2 | G80: 147 | H80: 229
A81: 38745 | B81: 0.52291667 | C81: 85 | E81: - МЯГКАЯ КОРИЦА | F81: 2 | G81: 147 | H81: 229
... A164: 38883 | B164: 0.44823529 | C164: 35 | E164: МУЛЬТИАКТИВНЫЙ БАЛЬЗАМ ДЛЯ ГУБ SPF 15 THE ONE - РОЗОВЫЙ | F164: 5 | G164: 301 | H164: 469
E165: КАРАНДАШИ ДЛЯ ГЛАЗ И БРОВЕЙ, ПОДВОДКА ДЛЯ ГЛАЗ, ПОМАДА ДЛЯ БРОВЕЙ
A166: 35424 | B166: 0.49322034 | C166: 86 | E166: ЖИДКАЯ ПОДВОДКА ONCOLOUR - ЧЕРНЫЙ | F166: 3 | G166: 192 | H166: 299
A167: 41414 | B167: 0.27769231 | C167: 74 | E167: ДВУХСТОРОННИЙ КАРАНДАШ ДЛЯ БРОВЕЙ GIORDANI GOLD - СВЕТЛЫЙ КОРИЧНЕВЫЙ | F167: 9 | G167: 603 | H167: 939
A168: 41415 | B168: 0.27769231 | C168: 74 | E168: - СРЕДНИЙ КОРИЧНЕВЫЙ | F168: 9 | G168: 603 | H168: 939
A169: 41437 | B169: 0.27769231 | C169: 74 | E169: УХАЖИВАЮЩАЯ ПОДВОДКА ДЛЯ ГЛАЗ GG - ЧЁРНЫЙ | F169: 9 | G169: 603 | H169: 939
A170: 42417 | B170: 0.402 | C170: 78 | E170: КАРАНДАШ ДЛЯ ГЛАЗ THE ONE - ЧЁРНЫЙ | F170: 3 | G170: 192 | H170: 299
A171: 42418 | B171: 0.402 | C171: 78 | E171: - КОРИЧНЕВЫЙ | F171: 3 | G171: 192 | H171: 299
A172: 42779 | B172: 0.47714286 | C172: 78 | E172: СТОЙКИЙ МАРКЕР-ПОДВОДКА ДЛЯ ГЛАЗ В БОЛЬШОМ ОБЪЕМЕ THE ONE - ЧЕРНЫЙ | F172: 5 | G172: 352 | H172: 549
A173: 43206 | B173: 0.38941176 | C173: 79 | E173: ТУШЬ ДЛЯ БРОВЕЙ THE ONE - КОРИЧНЕВЫЙ | F173: 5 | G173: 333 | H173: 519
A174: 43207 | B174: 0.38941176 | C174: 79 | E174: - ТЁМНО-КОРИЧНЕВЫЙ | F174: 5 | G174: 333 | H174: 519
A175: 43985 | B175: 0.39217391 | C175: 79 | E175: МАРКЕР ДЛЯ БРОВЕЙ THE ONE - СВЕТЛО-КОРИЧНЕВЫЙ | F175: 7 | G175: 449 | H175: 699
A176: 43986 | B176: 0.39217391 | C176: 79 | E176: - КОРИЧНЕВЫЙ | F176: 7 | G176: 449 | H176: 699
A177: 43987 | B177: 0.39217391 | C177: 79 | E177: - ТЁМНО-КОРИЧНЕВЫЙ | F177: 7 | G177: 449 | H177: 699
... A180: 46595 | B180: 0.47176471 | C180: 35 | E180: ГЕЛЬ-ФИКСАТОР ДЛЯ БРОВЕЙ THE ONE | F180: 4 | G180: 288 | H180: 449
E181: ТУШЬ ДЛЯ РЕСНИЦ
A182: 38929 | B182: 0.49298246 | C182: 86 | E182: ОБЪЕМНАЯ ТУШЬ ДЛЯ РЕСНИЦ ONCOLOUR - ЧЕРНЫЙ | F182: 3 | G182: 186 | H182: 289
A183: 42123 | B183: 0.50128205 | C183: 76 | E183: ТУШЬ С ЭФФЕКТОМ ГИПНОТИЧЕСКОГО ВЗГЛЯДА THE ONE HYPNOTIC DEPTH - ЧЁРНЫЙ | F183: 4 | G183: 249 | H183: 389
A184: 42823 | B184: 0.35333333 | C184: 75 | E184: СУПЕРТУШЬ ДЛЯ РЕСНИЦ GIORDANI GOLD - ЧЁРНЫЙ | F184: 7 | G184: 436 | H184: 679
A185: 43135 | B185: 0.5525641 | C185: 77 | E185: ТУШЬ С ЭКСТРЕМАЛЬНЫМ ОБЪЁМОМ THE ONE TREMENDOUS - ЧЁРНЫЙ | F185: 3 | G185: 224 | H185: 349
A186: 43143 | B186: 0.5525641 | C186: 77 | E186: ТУШЬ С ЭФФЕКТОМ КОШАЧЬИХ ГЛАЗ THE ONE TREMENDOUS - ЧЁРНЫЙ | F186: 3 | G186: 224 | H186: 349
A187: 46549 | B187: 0.401 | C187: 77 | E187: ТУШЬ ДЛЯ РЕСНИЦ 360° С ЭФФЕКТОМ ПОДКРУЧИВАНИЯ THE ONE - ЧЁРНЫЙ | F187: 6 | G187: 384 | H187: 599
A188: 47480 | B188: 0.54659091 | C188: 76 | E188: ЦВЕТНАЯ ТУШЬ THE ONE HYPNOTIC COLOUR - ЯРКИЙ РОЗОВЫЙ | F188: 4 | G188: 256 | H188: 399
A189: 47533 | B189: 0.54659091 | C189: 76 | E189: - ТРЕНДОВЫЙ ФИОЛЕТОВЫЙ | F189: 4 | G189: 256 | H189: 399
A190: 47534 | B190: 0.54659091 | C190: 76 | E190: - ПРОХЛАДНЫЙ МЯТНЫЙ | F190: 4 | G190: 256 | H190: 399
A191: 44655 | B191: 0.35333333 | C191: 75 | E191: ВОДОСТОЙКАЯ СУПЕРТУШЬ ДЛЯ РЕСНИЦ GIORDANI GOLD | F191: 7 | G191: 436 | H191: 679
A192: 34750 | B192: 0.49298246 | C192: 86 | E192: УДЛИНЯЮЩАЯ ТУШЬ ДЛЯ РЕСНИЦ ONCOLOUR - ЧЕРНЫЙ | F192: 3 | G192: 186 | H192: 289
...
